{
"meta":{"test_sets":[],"test_metrics":[],"learn_metrics":[{"best_value":"Min","name":"Logloss"}],"launch_mode":"Train","parameters":"","iteration_count":1000,"learn_sets":["learn"],"name":"experiment"},
"iterations":[
{"learn":[0.6508590899],"iteration":0,"passed_time":0.003340936674,"remaining_time":3.337595738},
{"learn":[0.6105576705],"iteration":1,"passed_time":0.006825408309,"remaining_time":3.405878746},
{"learn":[0.5718524217],"iteration":2,"passed_time":0.01030321869,"remaining_time":3.424103012},
{"learn":[0.5432471367],"iteration":3,"passed_time":0.01405750898,"remaining_time":3.500319737},
{"learn":[0.5099779672],"iteration":4,"passed_time":0.01756145062,"remaining_time":3.494728674},
{"learn":[0.4874703338],"iteration":5,"passed_time":0.02103785344,"remaining_time":3.485271053},
{"learn":[0.4603472601],"iteration":6,"passed_time":0.02430401222,"remaining_time":3.447697734},
{"learn":[0.4384706693],"iteration":7,"passed_time":0.02747880857,"remaining_time":3.407372262},
{"learn":[0.4199541089],"iteration":8,"passed_time":0.05194661684,"remaining_time":5.719899699},
{"learn":[0.3982032203],"iteration":9,"passed_time":0.06488000858,"remaining_time":6.423120849},
{"learn":[0.3793169086],"iteration":10,"passed_time":0.07385235867,"remaining_time":6.639998429},
{"learn":[0.3628740709],"iteration":11,"passed_time":0.08050020692,"remaining_time":6.62785037},
{"learn":[0.3509429767],"iteration":12,"passed_time":0.08605708503,"remaining_time":6.533718686},
{"learn":[0.3411574765],"iteration":13,"passed_time":0.09098997382,"remaining_time":6.40829387},
{"learn":[0.3272514232],"iteration":14,"passed_time":0.09548518317,"remaining_time":6.270193695},
{"learn":[0.3140245003],"iteration":15,"passed_time":0.09951592633,"remaining_time":6.120229469},
{"learn":[0.3064083593],"iteration":16,"passed_time":0.1031306143,"remaining_time":5.963376108},
{"learn":[0.2955367679],"iteration":17,"passed_time":0.1070281398,"remaining_time":5.838979626},
{"learn":[0.2841806751],"iteration":18,"passed_time":0.1104505874,"remaining_time":5.702738225},
{"learn":[0.2738480829],"iteration":19,"passed_time":0.1138405404,"remaining_time":5.57818648},
{"learn":[0.2648063235],"iteration":20,"passed_time":0.1170764171,"remaining_time":5.457991062},
{"learn":[0.2557677585],"iteration":21,"passed_time":0.1199855039,"remaining_time":5.333901037},
{"learn":[0.248655553],"iteration":22,"passed_time":0.1228964394,"remaining_time":5.220427015},
{"learn":[0.2421217801],"iteration":23,"passed_time":0.1256142876,"remaining_time":5.108314362},
{"learn":[0.2364083043],"iteration":24,"passed_time":0.1287387365,"remaining_time":5.020810725},
{"learn":[0.2319459722],"iteration":25,"passed_time":0.1317785152,"remaining_time":4.936625916},
{"learn":[0.2288198805],"iteration":26,"passed_time":0.1349489135,"remaining_time":4.863158993},
{"learn":[0.2235845573],"iteration":27,"passed_time":0.1381989381,"remaining_time":4.797477422},
{"learn":[0.2188730626],"iteration":28,"passed_time":0.1415279046,"remaining_time":4.738744668},
{"learn":[0.2157094292],"iteration":29,"passed_time":0.1447216812,"remaining_time":4.679334358},
{"learn":[0.2115439762],"iteration":30,"passed_time":0.1479041844,"remaining_time":4.623198538},
{"learn":[0.2075748548],"iteration":31,"passed_time":0.1510453867,"remaining_time":4.569122948},
{"learn":[0.204971796],"iteration":32,"passed_time":0.1541144053,"remaining_time":4.51601909},
{"learn":[0.2023023651],"iteration":33,"passed_time":0.1569270553,"remaining_time":4.458574571},
{"learn":[0.1990423819],"iteration":34,"passed_time":0.1596784125,"remaining_time":4.402561944},
{"learn":[0.1958188674],"iteration":35,"passed_time":0.1624910787,"remaining_time":4.351149995},
{"learn":[0.1929880196],"iteration":36,"passed_time":0.1653038576,"remaining_time":4.30236797},
{"learn":[0.1897369528],"iteration":37,"passed_time":0.1680680093,"remaining_time":4.25477434},
{"learn":[0.1875257436],"iteration":38,"passed_time":0.1708582601,"remaining_time":4.210122768},
{"learn":[0.1850369641],"iteration":39,"passed_time":0.1739875691,"remaining_time":4.175701659},
{"learn":[0.1827048965],"iteration":40,"passed_time":0.1770013355,"remaining_time":4.140104409},
{"learn":[0.1806177112],"iteration":41,"passed_time":0.179963554,"remaining_time":4.10488297},
{"learn":[0.1792276178],"iteration":42,"passed_time":0.1828541048,"remaining_time":4.069566938},
{"learn":[0.1777049111],"iteration":43,"passed_time":0.1856922912,"remaining_time":4.034587054},
{"learn":[0.1763268463],"iteration":44,"passed_time":0.1886266278,"remaining_time":4.003076212},
{"learn":[0.1750233132],"iteration":45,"passed_time":0.1915211151,"remaining_time":3.971981388},
{"learn":[0.1732066887],"iteration":46,"passed_time":0.1943523243,"remaining_time":3.940803511},
{"learn":[0.1716795618],"iteration":47,"passed_time":0.1973583946,"remaining_time":3.914274826},
{"learn":[0.1702359321],"iteration":48,"passed_time":0.2004596642,"remaining_time":3.89055389},
{"learn":[0.1693735376],"iteration":49,"passed_time":0.2034340622,"remaining_time":3.865247181},
{"learn":[0.1677635869],"iteration":50,"passed_time":0.2064588987,"remaining_time":3.841754801},
{"learn":[0.1666219532],"iteration":51,"passed_time":0.2094225433,"remaining_time":3.817934058},
{"learn":[0.1653923214],"iteration":52,"passed_time":0.2124031201,"remaining_time":3.795202919},
{"learn":[0.1644720489],"iteration":53,"passed_time":0.2154774491,"remaining_time":3.774845683},
{"learn":[0.1631427235],"iteration":54,"passed_time":0.2182112206,"remaining_time":3.749265517},
{"learn":[0.1622106747],"iteration":55,"passed_time":0.2210272624,"remaining_time":3.725888137},
{"learn":[0.1610015263],"iteration":56,"passed_time":0.2238505707,"remaining_time":3.703352424},
{"learn":[0.159926776],"iteration":57,"passed_time":0.2266571508,"remaining_time":3.681224759},
{"learn":[0.1592919],"iteration":58,"passed_time":0.2295710849,"remaining_time":3.661464253},
{"learn":[0.1583392522],"iteration":59,"passed_time":0.232340204,"remaining_time":3.63999653},
{"learn":[0.1575714866],"iteration":60,"passed_time":0.2351212218,"remaining_time":3.619325038},
{"learn":[0.1567806054],"iteration":61,"passed_time":0.2378949121,"remaining_time":3.599119799},
{"learn":[0.1562152955],"iteration":62,"passed_time":0.2409460726,"remaining_time":3.583594762},
{"learn":[0.1556644958],"iteration":63,"passed_time":0.2815066764,"remaining_time":4.117035143},
{"learn":[0.1548692174],"iteration":64,"passed_time":0.2978036639,"remaining_time":4.283791165},
{"learn":[0.1542771067],"iteration":65,"passed_time":0.3089623276,"remaining_time":4.372285061},
{"learn":[0.1538115631],"iteration":66,"passed_time":0.3173194004,"remaining_time":4.418791053},
{"learn":[0.153395474],"iteration":67,"passed_time":0.3234402806,"remaining_time":4.433034435},
{"learn":[0.1529084311],"iteration":68,"passed_time":0.3284945606,"remaining_time":4.432296173},
{"learn":[0.1525325606],"iteration":69,"passed_time":0.3331762849,"remaining_time":4.426484929},
{"learn":[0.1519127206],"iteration":70,"passed_time":0.3375512048,"remaining_time":4.416691116},
{"learn":[0.1513806166],"iteration":71,"passed_time":0.3412005204,"remaining_time":4.397695596},
{"learn":[0.1510245072],"iteration":72,"passed_time":0.3448202202,"remaining_time":4.378744441},
{"learn":[0.1505776056],"iteration":73,"passed_time":0.347953283,"remaining_time":4.354118109},
{"learn":[0.1499550526],"iteration":74,"passed_time":0.3510121134,"remaining_time":4.329149398},
{"learn":[0.1494599071],"iteration":75,"passed_time":0.3538836431,"remaining_time":4.302480081},
{"learn":[0.1488984137],"iteration":76,"passed_time":0.356631698,"remaining_time":4.274948796},
{"learn":[0.1483428925],"iteration":77,"passed_time":0.3594931792,"remaining_time":4.249393734},
{"learn":[0.1477872614],"iteration":78,"passed_time":0.3623520593,"remaining_time":4.224382869},
{"learn":[0.1473635189],"iteration":79,"passed_time":0.3652108683,"remaining_time":4.199924985},
{"learn":[0.1469023993],"iteration":80,"passed_time":0.3681333193,"remaining_time":4.176722475},
{"learn":[0.1466670102],"iteration":81,"passed_time":0.371193901,"remaining_time":4.15556099},
{"learn":[0.1462329428],"iteration":82,"passed_time":0.3740020258,"remaining_time":4.132046478},
{"learn":[0.1458574845],"iteration":83,"passed_time":0.3767340524,"remaining_time":4.108195143},
{"learn":[0.1455142563],"iteration":84,"passed_time":0.3794874113,"remaining_time":4.085070369},
{"learn":[0.1452414612],"iteration":85,"passed_time":0.3822900506,"remaining_time":4.062943096},
{"learn":[0.1449811692],"iteration":86,"passed_time":0.3850643319,"remaining_time":4.040962471},
{"learn":[0.1446967481],"iteration":87,"passed_time":0.3878288524,"remaining_time":4.019317198},
{"learn":[0.1443499349],"iteration":88,"passed_time":0.3906133922,"remaining_time":3.998301127},
{"learn":[0.1440637876],"iteration":89,"passed_time":0.3932856437,"remaining_time":3.976554842},
{"learn":[0.1437035984],"iteration":90,"passed_time":0.3960331691,"remaining_time":3.955979678},
{"learn":[0.1434161466],"iteration":91,"passed_time":0.3988262915,"remaining_time":3.936242094},
{"learn":[0.1431013116],"iteration":92,"passed_time":0.401692975,"remaining_time":3.917586326},
{"learn":[0.1427754436],"iteration":93,"passed_time":0.4046235177,"remaining_time":3.89988199},
{"learn":[0.1425204333],"iteration":94,"passed_time":0.4077438532,"remaining_time":3.884296707},
{"learn":[0.1422490156],"iteration":95,"passed_time":0.4105483204,"remaining_time":3.865996684},
{"learn":[0.1417852289],"iteration":96,"passed_time":0.4136376214,"remaining_time":3.850667754},
{"learn":[0.1414783294],"iteration":97,"passed_time":0.4165597758,"remaining_time":3.834050181},
{"learn":[0.1410955601],"iteration":98,"passed_time":0.4195026015,"remaining_time":3.817897414},
{"learn":[0.1408670296],"iteration":99,"passed_time":0.4223347489,"remaining_time":3.80101274},
{"learn":[0.1405518844],"iteration":100,"passed_time":0.4250702496,"remaining_time":3.783546083},
{"learn":[0.1401972588],"iteration":101,"passed_time":0.4278519936,"remaining_time":3.766775395},
{"learn":[0.1399400263],"iteration":102,"passed_time":0.4306615495,"remaining_time":3.750518543},
{"learn":[0.1396979529],"iteration":103,"passed_time":0.4334300012,"remaining_time":3.734166164},
{"learn":[0.1395162153],"iteration":104,"passed_time":0.4362946432,"remaining_time":3.718892435},
{"learn":[0.139270195],"iteration":105,"passed_time":0.4392200547,"remaining_time":3.704365367},
{"learn":[0.1389556473],"iteration":106,"passed_time":0.4421605176,"remaining_time":3.690180768},
{"learn":[0.138751303],"iteration":107,"passed_time":0.4449912303,"remaining_time":3.675297939},
{"learn":[0.1384552457],"iteration":108,"passed_time":0.4477570997,"remaining_time":3.660106201},
{"learn":[0.1381335174],"iteration":109,"passed_time":0.4505235497,"remaining_time":3.645145084},
{"learn":[0.1378875279],"iteration":110,"passed_time":0.4532267269,"remaining_time":3.629896939},
{"learn":[0.1375802522],"iteration":111,"passed_time":0.4558866834,"remaining_time":3.614530132},
{"learn":[0.137353831],"iteration":112,"passed_time":0.4586271983,"remaining_time":3.600020574},
{"learn":[0.1371606028],"iteration":113,"passed_time":0.4614896537,"remaining_time":3.586665203},
{"learn":[0.1369895483],"iteration":114,"passed_time":0.4644514635,"remaining_time":3.574256915},
{"learn":[0.1367747493],"iteration":115,"passed_time":0.4673212522,"remaining_time":3.561310233},
{"learn":[0.1365861235],"iteration":116,"passed_time":0.4703039964,"remaining_time":3.54938828},
{"learn":[0.1362909686],"iteration":117,"passed_time":0.4731081754,"remaining_time":3.536283142},
{"learn":[0.1360614722],"iteration":118,"passed_time":0.4758857237,"remaining_time":3.523153971},
{"learn":[0.1359313003],"iteration":119,"passed_time":0.478610376,"remaining_time":3.509809424},
{"learn":[0.1357162457],"iteration":120,"passed_time":0.4813760573,"remaining_time":3.496938466},
{"learn":[0.1355012009],"iteration":121,"passed_time":0.4841437511,"remaining_time":3.484247651},
{"learn":[0.1352216181],"iteration":122,"passed_time":0.4868532747,"remaining_time":3.47130343},
{"learn":[0.1349198815],"iteration":123,"passed_time":0.4897184494,"remaining_time":3.459623885},
{"learn":[0.1346798591],"iteration":124,"passed_time":0.4924976911,"remaining_time":3.447483838},
{"learn":[0.1344614435],"iteration":125,"passed_time":0.4953321002,"remaining_time":3.435875044},
{"learn":[0.1342316436],"iteration":126,"passed_time":0.4982580759,"remaining_time":3.425033861},
{"learn":[0.1339922759],"iteration":127,"passed_time":0.5011509552,"remaining_time":3.414090882},
{"learn":[0.1337885774],"iteration":128,"passed_time":0.5041137071,"remaining_time":3.403744488},
{"learn":[0.1335900337],"iteration":129,"passed_time":0.5069762293,"remaining_time":3.392840919},
{"learn":[0.1334222206],"iteration":130,"passed_time":0.5098112626,"remaining_time":3.381877765},
{"learn":[0.1332508525],"iteration":131,"passed_time":0.5125291628,"remaining_time":3.370267525},
{"learn":[0.1330339034],"iteration":132,"passed_time":0.5153249586,"remaining_time":3.35929879},
{"learn":[0.1329020031],"iteration":133,"passed_time":0.5180673856,"remaining_time":3.348107134},
{"learn":[0.1326346849],"iteration":134,"passed_time":0.5210229981,"remaining_time":3.338406617},
{"learn":[0.1325076606],"iteration":135,"passed_time":0.5238790112,"remaining_time":3.328172542},
{"learn":[0.1323216821],"iteration":136,"passed_time":0.5267427251,"remaining_time":3.318094684},
{"learn":[0.1321101667],"iteration":137,"passed_time":0.5297697282,"remaining_time":3.309141346},
{"learn":[0.131853144],"iteration":138,"passed_time":0.5327649497,"remaining_time":3.300076415},
{"learn":[0.1316601806],"iteration":139,"passed_time":0.5357347777,"remaining_time":3.290942206},
{"learn":[0.131406065],"iteration":140,"passed_time":0.5387502313,"remaining_time":3.282173395},
{"learn":[0.1312443632],"iteration":141,"passed_time":0.5416531108,"remaining_time":3.272805416},
{"learn":[0.1309515988],"iteration":142,"passed_time":0.5445236381,"remaining_time":3.263333971},
{"learn":[0.1307500656],"iteration":143,"passed_time":0.5475251716,"remaining_time":3.254732965},
{"learn":[0.1305262534],"iteration":144,"passed_time":0.5503229212,"remaining_time":3.24500757},
{"learn":[0.1302630484],"iteration":145,"passed_time":0.5530464533,"remaining_time":3.234942953},
{"learn":[0.1301032246],"iteration":146,"passed_time":0.5559478464,"remaining_time":3.226010292},
{"learn":[0.1298293388],"iteration":147,"passed_time":0.5587447878,"remaining_time":3.216557833},
{"learn":[0.1296871965],"iteration":148,"passed_time":0.5614864817,"remaining_time":3.206879167},
{"learn":[0.1293793081],"iteration":149,"passed_time":0.564512978,"remaining_time":3.198906875},
{"learn":[0.1292309609],"iteration":150,"passed_time":0.5673603418,"remaining_time":3.189992915},
{"learn":[0.1289919392],"iteration":151,"passed_time":0.5701679953,"remaining_time":3.180937237},
{"learn":[0.1287877762],"iteration":152,"passed_time":0.5729674522,"remaining_time":3.171917856},
{"learn":[0.1285943562],"iteration":153,"passed_time":0.5757443384,"remaining_time":3.162855262},
{"learn":[0.1284495637],"iteration":154,"passed_time":0.5785425356,"remaining_time":3.153989952},
{"learn":[0.1282108007],"iteration":155,"passed_time":0.5814163354,"remaining_time":3.145611456},
{"learn":[0.1279647781],"iteration":156,"passed_time":0.5841972512,"remaining_time":3.136804349},
{"learn":[0.1278182053],"iteration":157,"passed_time":0.5870485913,"remaining_time":3.128448822},
{"learn":[0.1276619329],"iteration":158,"passed_time":0.5899195485,"remaining_time":3.120266291},
{"learn":[0.1274829843],"iteration":159,"passed_time":0.5928045776,"remaining_time":3.112224032},
{"learn":[0.1272472636],"iteration":160,"passed_time":0.5955685029,"remaining_time":3.103614745},
{"learn":[0.1270781838],"iteration":161,"passed_time":0.5986414082,"remaining_time":3.096675926},
{"learn":[0.1268636153],"iteration":162,"passed_time":0.6016985509,"remaining_time":3.089703602},
{"learn":[0.1267229047],"iteration":163,"passed_time":0.6048195196,"remaining_time":3.08310438},
{"learn":[0.1265565978],"iteration":164,"passed_time":0.6077835133,"remaining_time":3.075752931},
{"learn":[0.1263035003],"iteration":165,"passed_time":0.6105162179,"remaining_time":3.067292324},
{"learn":[0.1260982572],"iteration":166,"passed_time":0.6139650363,"remaining_time":3.062472307},
{"learn":[0.1259079399],"iteration":167,"passed_time":0.6167171061,"remaining_time":3.054218049},
{"learn":[0.125728187],"iteration":168,"passed_time":0.6194868973,"remaining_time":3.046116046},
{"learn":[0.1255430852],"iteration":169,"passed_time":0.622352249,"remaining_time":3.038543333},
{"learn":[0.1254349906],"iteration":170,"passed_time":0.6253549108,"remaining_time":3.031691351},
{"learn":[0.1252618651],"iteration":171,"passed_time":0.6284290256,"remaining_time":3.0252281},
{"learn":[0.1250913399],"iteration":172,"passed_time":0.6313642668,"remaining_time":3.018140166},
{"learn":[0.1249264536],"iteration":173,"passed_time":0.6343945985,"remaining_time":3.01155137},
{"learn":[0.1246713937],"iteration":174,"passed_time":0.6374294854,"remaining_time":3.005024717},
{"learn":[0.124534272],"iteration":175,"passed_time":0.6405422562,"remaining_time":2.998902381},
{"learn":[0.1242533337],"iteration":176,"passed_time":0.6661532709,"remaining_time":3.097424531},
{"learn":[0.124097329],"iteration":177,"passed_time":0.6772122465,"remaining_time":3.127350936},
{"learn":[0.1238865799],"iteration":178,"passed_time":0.6849220292,"remaining_time":3.141458022},
{"learn":[0.1237349573],"iteration":179,"passed_time":0.6914597465,"remaining_time":3.14998329},
{"learn":[0.1235986686],"iteration":180,"passed_time":0.6965844376,"remaining_time":3.151948367},
{"learn":[0.1234274374],"iteration":181,"passed_time":0.7011426018,"remaining_time":3.151289276},
{"learn":[0.1232686496],"iteration":182,"passed_time":0.705303649,"remaining_time":3.148814651},
{"learn":[0.1230971522],"iteration":183,"passed_time":0.7087939266,"remaining_time":3.143346979},
{"learn":[0.1229569837],"iteration":184,"passed_time":0.7123269062,"remaining_time":3.138088803},
{"learn":[0.1228252877],"iteration":185,"passed_time":0.7154600984,"remaining_time":3.131099571},
{"learn":[0.1226315146],"iteration":186,"passed_time":0.7185078312,"remaining_time":3.123780036},
{"learn":[0.1224309211],"iteration":187,"passed_time":0.7212883955,"remaining_time":3.115352006},
{"learn":[0.1223345719],"iteration":188,"passed_time":0.7243683715,"remaining_time":3.108268515},
{"learn":[0.1221529771],"iteration":189,"passed_time":0.7272501838,"remaining_time":3.100382362},
{"learn":[0.1219571895],"iteration":190,"passed_time":0.7300544211,"remaining_time":3.092220035},
{"learn":[0.1218623589],"iteration":191,"passed_time":0.7329807789,"remaining_time":3.084627445},
{"learn":[0.1217475048],"iteration":192,"passed_time":0.7358186134,"remaining_time":3.076713062},
{"learn":[0.121486555],"iteration":193,"passed_time":0.7387631194,"remaining_time":3.069294197},
{"learn":[0.1213735022],"iteration":194,"passed_time":0.7434046777,"remaining_time":3.068927003},
{"learn":[0.1211410639],"iteration":195,"passed_time":0.7500627289,"remaining_time":3.076787929},
{"learn":[0.1209954831],"iteration":196,"passed_time":0.7549074717,"remaining_time":3.077110151},
{"learn":[0.120857825],"iteration":197,"passed_time":0.75837323,"remaining_time":3.071794598},
{"learn":[0.1207600969],"iteration":198,"passed_time":0.7615558302,"remaining_time":3.065357889},
{"learn":[0.1206425953],"iteration":199,"passed_time":0.7645380699,"remaining_time":3.05815228},
{"learn":[0.1204278847],"iteration":200,"passed_time":0.7675175111,"remaining_time":3.050977569},
{"learn":[0.1202759527],"iteration":201,"passed_time":0.7704183916,"remaining_time":3.043534042},
{"learn":[0.1201006823],"iteration":202,"passed_time":0.7733816881,"remaining_time":3.036380322},
{"learn":[0.1199102834],"iteration":203,"passed_time":0.7762888127,"remaining_time":3.029048504},
{"learn":[0.1197319766],"iteration":204,"passed_time":0.7792205505,"remaining_time":3.021855306},
{"learn":[0.1195817706],"iteration":205,"passed_time":0.7820916711,"remaining_time":3.014469839},
{"learn":[0.1194241068],"iteration":206,"passed_time":0.7853259521,"remaining_time":3.008519227},
{"learn":[0.119295862],"iteration":207,"passed_time":0.788262322,"remaining_time":3.00146038},
{"learn":[0.1191371253],"iteration":208,"passed_time":0.7911633435,"remaining_time":2.9943072},
{"learn":[0.1189807092],"iteration":209,"passed_time":0.7939767819,"remaining_time":2.986865037},
{"learn":[0.1188661626],"iteration":210,"passed_time":0.796713679,"remaining_time":2.979180534},
{"learn":[0.118744117],"iteration":211,"passed_time":0.7995144955,"remaining_time":2.971780295},
{"learn":[0.1185741131],"iteration":212,"passed_time":0.8023936061,"remaining_time":2.964712526},
{"learn":[0.1184656074],"iteration":213,"passed_time":0.8050887736,"remaining_time":2.957008299},
{"learn":[0.11825888],"iteration":214,"passed_time":0.8079109293,"remaining_time":2.949814323},
{"learn":[0.1181621758],"iteration":215,"passed_time":0.8106615236,"remaining_time":2.942401086},
{"learn":[0.1179802542],"iteration":216,"passed_time":0.8134279751,"remaining_time":2.935088039},
{"learn":[0.1178966555],"iteration":217,"passed_time":0.8162247288,"remaining_time":2.927925403},
{"learn":[0.1177944292],"iteration":218,"passed_time":0.8272879186,"remaining_time":2.950282486},
{"learn":[0.117613551],"iteration":219,"passed_time":0.8299766157,"remaining_time":2.942644365},
{"learn":[0.1174332171],"iteration":220,"passed_time":0.83264361,"remaining_time":2.934974535},
{"learn":[0.1172876006],"iteration":221,"passed_time":0.8354313312,"remaining_time":2.927772863},
{"learn":[0.1170591868],"iteration":222,"passed_time":0.8380331113,"remaining_time":2.919962904},
{"learn":[0.1168660035],"iteration":223,"passed_time":0.8408010944,"remaining_time":2.91277522},
{"learn":[0.1166595612],"iteration":224,"passed_time":0.843495655,"remaining_time":2.905373923},
{"learn":[0.1165260896],"iteration":225,"passed_time":0.8462078787,"remaining_time":2.89807477},
{"learn":[0.1163960575],"iteration":226,"passed_time":0.84882788,"remaining_time":2.890501988},
{"learn":[0.1162775174],"iteration":227,"passed_time":0.8517177167,"remaining_time":2.883886304},
{"learn":[0.1160965441],"iteration":228,"passed_time":0.8546143578,"remaining_time":2.877326069},
{"learn":[0.1159778647],"iteration":229,"passed_time":0.8574914324,"remaining_time":2.870732187},
{"learn":[0.1158879555],"iteration":230,"passed_time":0.8603404189,"remaining_time":2.864076979},
{"learn":[0.1156855305],"iteration":231,"passed_time":0.8631183763,"remaining_time":2.857219453},
{"learn":[0.1155800082],"iteration":232,"passed_time":0.8658768359,"remaining_time":2.85033276},
{"learn":[0.1154434633],"iteration":233,"passed_time":0.8686335445,"remaining_time":2.84347562},
{"learn":[0.1152832787],"iteration":234,"passed_time":0.8713889679,"remaining_time":2.836649193},
{"learn":[0.1151873666],"iteration":235,"passed_time":0.8741048604,"remaining_time":2.829729294},
{"learn":[0.1150676081],"iteration":236,"passed_time":0.8767858783,"remaining_time":2.822732596},
{"learn":[0.1148766103],"iteration":237,"passed_time":0.8795118953,"remaining_time":2.815916236},
{"learn":[0.1147879547],"iteration":238,"passed_time":0.8822567906,"remaining_time":2.809194216},
{"learn":[0.1147011572],"iteration":239,"passed_time":0.8853387794,"remaining_time":2.803572802},
{"learn":[0.1145567268],"iteration":240,"passed_time":0.8883366082,"remaining_time":2.797707409},
{"learn":[0.1145106437],"iteration":241,"passed_time":0.8914266393,"remaining_time":2.792154515},
{"learn":[0.1143518098],"iteration":242,"passed_time":0.8945377256,"remaining_time":2.786687483},
{"learn":[0.1141472372],"iteration":243,"passed_time":0.8975784672,"remaining_time":2.781021808},
{"learn":[0.1140515369],"iteration":244,"passed_time":0.9004767384,"remaining_time":2.774938521},
{"learn":[0.1139656033],"iteration":245,"passed_time":0.903382306,"remaining_time":2.768903491},
{"learn":[0.1138448577],"iteration":246,"passed_time":0.9062892818,"remaining_time":2.762898094},
{"learn":[0.1137168651],"iteration":247,"passed_time":0.9091311714,"remaining_time":2.756720326},
{"learn":[0.1136207068],"iteration":248,"passed_time":0.911966558,"remaining_time":2.750549739},
{"learn":[0.113523736],"iteration":249,"passed_time":0.9149191023,"remaining_time":2.744757307},
{"learn":[0.1134112092],"iteration":250,"passed_time":0.9179007278,"remaining_time":2.739074283},
{"learn":[0.1132826129],"iteration":251,"passed_time":0.9208863466,"remaining_time":2.733424553},
{"learn":[0.1131531439],"iteration":252,"passed_time":0.923865344,"remaining_time":2.727776332},
{"learn":[0.1130491783],"iteration":253,"passed_time":0.9265935785,"remaining_time":2.721412636},
{"learn":[0.1128803379],"iteration":254,"passed_time":0.9293863444,"remaining_time":2.715265987},
{"learn":[0.1125971147],"iteration":255,"passed_time":0.9322115381,"remaining_time":2.709239783},
{"learn":[0.1123892579],"iteration":256,"passed_time":0.9352642078,"remaining_time":2.703896134},
{"learn":[0.1122769185],"iteration":257,"passed_time":0.938238539,"remaining_time":2.698344945},
{"learn":[0.1121115167],"iteration":258,"passed_time":0.941127403,"remaining_time":2.692569134},
{"learn":[0.1120265487],"iteration":259,"passed_time":0.9439754806,"remaining_time":2.686699445},
{"learn":[0.1119696254],"iteration":260,"passed_time":0.9484746002,"remaining_time":2.685527699},
{"learn":[0.1118649229],"iteration":261,"passed_time":0.9520351116,"remaining_time":2.681686688},
{"learn":[0.1117313778],"iteration":262,"passed_time":0.9554911182,"remaining_time":2.677554958},
{"learn":[0.1115999231],"iteration":263,"passed_time":0.9592752471,"remaining_time":2.674343113},
{"learn":[0.1114971785],"iteration":264,"passed_time":0.9630559835,"remaining_time":2.671117539},
{"learn":[0.1114103071],"iteration":265,"passed_time":0.9663321683,"remaining_time":2.666495532},
{"learn":[0.1113330245],"iteration":266,"passed_time":0.9694478099,"remaining_time":2.661442864},
{"learn":[0.1111967817],"iteration":267,"passed_time":0.9726179996,"remaining_time":2.656553641},
{"learn":[0.1110805904],"iteration":268,"passed_time":0.9757963666,"remaining_time":2.65169942},
{"learn":[0.1109645308],"iteration":269,"passed_time":0.9791128894,"remaining_time":2.647231145},
{"learn":[0.1108341747],"iteration":270,"passed_time":0.9822872736,"remaining_time":2.642389013},
{"learn":[0.1107550025],"iteration":271,"passed_time":0.9853945273,"remaining_time":2.63737947},
{"learn":[0.1106278054],"iteration":272,"passed_time":0.9883541203,"remaining_time":2.631990643},
{"learn":[0.1104851279],"iteration":273,"passed_time":0.9913968817,"remaining_time":2.626839913},
{"learn":[0.1103835039],"iteration":274,"passed_time":0.9942883299,"remaining_time":2.621305597},
{"learn":[0.110274496],"iteration":275,"passed_time":0.997151445,"remaining_time":2.615716109},
{"learn":[0.1101689411],"iteration":276,"passed_time":0.9999594006,"remaining_time":2.610002334},
{"learn":[0.1100544415],"iteration":277,"passed_time":1.00270001,"remaining_time":2.604134558},
{"learn":[0.1098937663],"iteration":278,"passed_time":1.00552461,"remaining_time":2.598506251},
{"learn":[0.1097642802],"iteration":279,"passed_time":1.008366191,"remaining_time":2.592941634},
{"learn":[0.1095737138],"iteration":280,"passed_time":1.011151707,"remaining_time":2.587252945},
{"learn":[0.1094419111],"iteration":281,"passed_time":1.014153752,"remaining_time":2.58213615},
{"learn":[0.1092754557],"iteration":282,"passed_time":1.017229175,"remaining_time":2.577220207},
{"learn":[0.1091313852],"iteration":283,"passed_time":1.020372791,"remaining_time":2.57248915},
{"learn":[0.108969508],"iteration":284,"passed_time":1.023426922,"remaining_time":2.567544734},
{"learn":[0.1088868827],"iteration":285,"passed_time":1.026414955,"remaining_time":2.562448523},
{"learn":[0.1088087087],"iteration":286,"passed_time":1.029354257,"remaining_time":2.557245942},
{"learn":[0.1087388927],"iteration":287,"passed_time":1.032202982,"remaining_time":2.55183515},
{"learn":[0.1086424882],"iteration":288,"passed_time":1.03519117,"remaining_time":2.546785197},
{"learn":[0.1085173971],"iteration":289,"passed_time":1.038047602,"remaining_time":2.541426889},
{"learn":[0.1084111627],"iteration":290,"passed_time":1.040870169,"remaining_time":2.536003264},
{"learn":[0.108255268],"iteration":291,"passed_time":1.044077105,"remaining_time":2.531529418},
{"learn":[0.1081669094],"iteration":292,"passed_time":1.047084982,"remaining_time":2.526583899},
{"learn":[0.107998128],"iteration":293,"passed_time":1.05025273,"remaining_time":2.522035468},
{"learn":[0.1079088993],"iteration":294,"passed_time":1.053283101,"remaining_time":2.517168088},
{"learn":[0.107818788],"iteration":295,"passed_time":1.056494788,"remaining_time":2.512744361},
{"learn":[0.1076858723],"iteration":296,"passed_time":1.060836568,"remaining_time":2.511003727},
{"learn":[0.1075676894],"iteration":297,"passed_time":1.064625339,"remaining_time":2.507942912},
{"learn":[0.1073743948],"iteration":298,"passed_time":1.068013504,"remaining_time":2.503938015},
{"learn":[0.1072592576],"iteration":299,"passed_time":1.071666541,"remaining_time":2.500555263},
{"learn":[0.1070805701],"iteration":300,"passed_time":1.074655294,"remaining_time":2.495628074},
{"learn":[0.1069596217],"iteration":301,"passed_time":1.077856255,"remaining_time":2.491204193},
{"learn":[0.1068814523],"iteration":302,"passed_time":1.08103748,"remaining_time":2.486742983},
{"learn":[0.1067485789],"iteration":303,"passed_time":1.084172716,"remaining_time":2.482184901},
{"learn":[0.1066144688],"iteration":304,"passed_time":1.087420661,"remaining_time":2.477892981},
{"learn":[0.106461124],"iteration":305,"passed_time":1.090491697,"remaining_time":2.473206658},
{"learn":[0.106314785],"iteration":306,"passed_time":1.093589618,"remaining_time":2.468591547},
{"learn":[0.1061676558],"iteration":307,"passed_time":1.106873697,"remaining_time":2.486872073},
{"learn":[0.1060814758],"iteration":308,"passed_time":1.113777146,"remaining_time":2.490679637},
{"learn":[0.1060024768],"iteration":309,"passed_time":1.119682574,"remaining_time":2.492196696},
{"learn":[0.1059181894],"iteration":310,"passed_time":1.124605187,"remaining_time":2.491488662},
{"learn":[0.1058513218],"iteration":311,"passed_time":1.128742894,"remaining_time":2.489022792},
{"learn":[0.1057913731],"iteration":312,"passed_time":1.13256533,"remaining_time":2.485854254},
{"learn":[0.1056706026],"iteration":313,"passed_time":1.136228252,"remaining_time":2.48233306},
{"learn":[0.1055640557],"iteration":314,"passed_time":1.139535121,"remaining_time":2.478036693},
{"learn":[0.1054492328],"iteration":315,"passed_time":1.143086934,"remaining_time":2.474276782},
{"learn":[0.1053000508],"iteration":316,"passed_time":1.146428743,"remaining_time":2.470065715},
{"learn":[0.1051575296],"iteration":317,"passed_time":1.164663689,"remaining_time":2.497800743},
{"learn":[0.1049947107],"iteration":318,"passed_time":1.167399307,"remaining_time":2.492159649},
{"learn":[0.104914537],"iteration":319,"passed_time":1.170349426,"remaining_time":2.48699253},
{"learn":[0.1047625434],"iteration":320,"passed_time":1.17320775,"remaining_time":2.481645053},
{"learn":[0.1046993283],"iteration":321,"passed_time":1.176207466,"remaining_time":2.476610751},
{"learn":[0.1046114895],"iteration":322,"passed_time":1.179576874,"remaining_time":2.472363913},
{"learn":[0.1045075566],"iteration":323,"passed_time":1.182641059,"remaining_time":2.467485666},
{"learn":[0.1044203797],"iteration":324,"passed_time":1.185551293,"remaining_time":2.462298839},
{"learn":[0.104279097],"iteration":325,"passed_time":1.188416903,"remaining_time":2.457033719},
{"learn":[0.104124553],"iteration":326,"passed_time":1.191421131,"remaining_time":2.452068566},
{"learn":[0.1039792941],"iteration":327,"passed_time":1.19460205,"remaining_time":2.44747737},
{"learn":[0.1039265134],"iteration":328,"passed_time":1.197550832,"remaining_time":2.442421302},
{"learn":[0.1038392678],"iteration":329,"passed_time":1.200462119,"remaining_time":2.437301879},
{"learn":[0.1038024858],"iteration":330,"passed_time":1.203293403,"remaining_time":2.432034098},
{"learn":[0.1037504029],"iteration":331,"passed_time":1.206294389,"remaining_time":2.427122445},
{"learn":[0.1036409903],"iteration":332,"passed_time":1.20953607,"remaining_time":2.422704381},
{"learn":[0.1035546527],"iteration":333,"passed_time":1.212404955,"remaining_time":2.417550001},
{"learn":[0.1034100609],"iteration":334,"passed_time":1.215235464,"remaining_time":2.412333086},
{"learn":[0.1032113592],"iteration":335,"passed_time":1.218185314,"remaining_time":2.407366216},
{"learn":[0.103107833],"iteration":336,"passed_time":1.220912351,"remaining_time":2.401972963},
{"learn":[0.1030257053],"iteration":337,"passed_time":1.223656659,"remaining_time":2.396629314},
{"learn":[0.1029252321],"iteration":338,"passed_time":1.227129287,"remaining_time":2.392721118},
{"learn":[0.1028471617],"iteration":339,"passed_time":1.229840683,"remaining_time":2.387337797},
{"learn":[0.1027694488],"iteration":340,"passed_time":1.232681459,"remaining_time":2.382220181},
{"learn":[0.1027256409],"iteration":341,"passed_time":1.235291065,"remaining_time":2.376671113},
{"learn":[0.1026680646],"iteration":342,"passed_time":1.238119212,"remaining_time":2.371557791},
{"learn":[0.1025055045],"iteration":343,"passed_time":1.241059662,"remaining_time":2.366671913},
{"learn":[0.1023757073],"iteration":344,"passed_time":1.244153287,"remaining_time":2.362088124},
{"learn":[0.1022504786],"iteration":345,"passed_time":1.247406351,"remaining_time":2.357814317},
{"learn":[0.1021767162],"iteration":346,"passed_time":1.250538294,"remaining_time":2.353318461},
{"learn":[0.1020710656],"iteration":347,"passed_time":1.253676704,"remaining_time":2.34884256},
{"learn":[0.1019969707],"iteration":348,"passed_time":1.256668332,"remaining_time":2.344100528},
{"learn":[0.1018095145],"iteration":349,"passed_time":1.25973203,"remaining_time":2.339502342},
{"learn":[0.1017506628],"iteration":350,"passed_time":1.262707365,"remaining_time":2.334749515},
{"learn":[0.1016282026],"iteration":351,"passed_time":1.26555371,"remaining_time":2.329769329},
{"learn":[0.1015316963],"iteration":352,"passed_time":1.268535915,"remaining_time":2.325050246},
{"learn":[0.1014520673],"iteration":353,"passed_time":1.27157358,"remaining_time":2.320442182},
{"learn":[0.1013927097],"iteration":354,"passed_time":1.274611753,"remaining_time":2.315843889},
{"learn":[0.1012290635],"iteration":355,"passed_time":1.277454673,"remaining_time":2.310901149},
{"learn":[0.1011110894],"iteration":356,"passed_time":1.280478709,"remaining_time":2.306296386},
{"learn":[0.100967316],"iteration":357,"passed_time":1.283343968,"remaining_time":2.301415719},
{"learn":[0.1008710328],"iteration":358,"passed_time":1.286190717,"remaining_time":2.29651323},
{"learn":[0.1008296945],"iteration":359,"passed_time":1.288959106,"remaining_time":2.291482855},
{"learn":[0.1007376711],"iteration":360,"passed_time":1.291772983,"remaining_time":2.28654553},
{"learn":[0.1005816791],"iteration":361,"passed_time":1.306873881,"remaining_time":2.303274961},
{"learn":[0.1004371712],"iteration":362,"passed_time":1.312998855,"remaining_time":2.30407788},
{"learn":[0.1003274146],"iteration":363,"passed_time":1.318235716,"remaining_time":2.303290976},
{"learn":[0.1001352453],"iteration":364,"passed_time":1.322897985,"remaining_time":2.301480056},
{"learn":[0.1000054061],"iteration":365,"passed_time":1.326918242,"remaining_time":2.298541436},
{"learn":[0.09993714701],"iteration":366,"passed_time":1.33036556,"remaining_time":2.294608718},
{"learn":[0.09984565125],"iteration":367,"passed_time":1.333755376,"remaining_time":2.290579886},
{"learn":[0.09977413618],"iteration":368,"passed_time":1.337164732,"remaining_time":2.286587929},
{"learn":[0.09967312485],"iteration":369,"passed_time":1.340328326,"remaining_time":2.282180664},
{"learn":[0.09959075363],"iteration":370,"passed_time":1.343172082,"remaining_time":2.277237842},
{"learn":[0.09950234564],"iteration":371,"passed_time":1.345963531,"remaining_time":2.272218003},
{"learn":[0.09936062278],"iteration":372,"passed_time":1.348726838,"remaining_time":2.267162808},
{"learn":[0.09930730834],"iteration":373,"passed_time":1.351512621,"remaining_time":2.262157488},
{"learn":[0.09917171583],"iteration":374,"passed_time":1.354299735,"remaining_time":2.257166224},
{"learn":[0.0990720031],"iteration":375,"passed_time":1.357088547,"remaining_time":2.252189503},
{"learn":[0.09898408858],"iteration":376,"passed_time":1.360133649,"remaining_time":2.247647914},
{"learn":[0.0988767879],"iteration":377,"passed_time":1.362955903,"remaining_time":2.242747545},
{"learn":[0.0987691112],"iteration":378,"passed_time":1.365768976,"remaining_time":2.237843099},
{"learn":[0.09866735082],"iteration":379,"passed_time":1.368666762,"remaining_time":2.233087874},
{"learn":[0.09856897658],"iteration":380,"passed_time":1.371591966,"remaining_time":2.228386947},
{"learn":[0.09837380485],"iteration":381,"passed_time":1.374628025,"remaining_time":2.223874658},
{"learn":[0.0982614592],"iteration":382,"passed_time":1.379019297,"remaining_time":2.22155328},
{"learn":[0.09820483644],"iteration":383,"passed_time":1.381761921,"remaining_time":2.216576415},
{"learn":[0.0981096935],"iteration":384,"passed_time":1.384582511,"remaining_time":2.211735699},
{"learn":[0.09800979152],"iteration":385,"passed_time":1.38735955,"remaining_time":2.206836176},
{"learn":[0.09794823646],"iteration":386,"passed_time":1.390054909,"remaining_time":2.201818241},
{"learn":[0.09783969172],"iteration":387,"passed_time":1.392887145,"remaining_time":2.197028177},
{"learn":[0.09770337771],"iteration":388,"passed_time":1.395694301,"remaining_time":2.192208786},
{"learn":[0.09757380627],"iteration":389,"passed_time":1.398528716,"remaining_time":2.187442351},
{"learn":[0.09742313291],"iteration":390,"passed_time":1.401462461,"remaining_time":2.182840508},
{"learn":[0.09734174405],"iteration":391,"passed_time":1.40459856,"remaining_time":2.178561032},
{"learn":[0.09720501435],"iteration":392,"passed_time":1.407986129,"remaining_time":2.174675777},
{"learn":[0.0971595583],"iteration":393,"passed_time":1.411034952,"remaining_time":2.170272033},
{"learn":[0.09703797674],"iteration":394,"passed_time":1.41408718,"remaining_time":2.165880364},
{"learn":[0.09690933253],"iteration":395,"passed_time":1.416923995,"remaining_time":2.161166901},
{"learn":[0.09677800933],"iteration":396,"passed_time":1.424758266,"remaining_time":2.164053487},
{"learn":[0.09667004499],"iteration":397,"passed_time":1.427659179,"remaining_time":2.159424185},
{"learn":[0.09661955168],"iteration":398,"passed_time":1.430683236,"remaining_time":2.154989035},
{"learn":[0.09651460081],"iteration":399,"passed_time":1.433626093,"remaining_time":2.15043914},
{"learn":[0.09649418049],"iteration":400,"passed_time":1.436583217,"remaining_time":2.14591857},
{"learn":[0.09634033599],"iteration":401,"passed_time":1.439474424,"remaining_time":2.141307725},
{"learn":[0.09622279696],"iteration":402,"passed_time":1.442368472,"remaining_time":2.136709622},
{"learn":[0.0961548905],"iteration":403,"passed_time":1.445128116,"remaining_time":2.131921677},
{"learn":[0.09605081875],"iteration":404,"passed_time":1.447866014,"remaining_time":2.127111798},
{"learn":[0.09596069601],"iteration":405,"passed_time":1.450571566,"remaining_time":2.122264804},
{"learn":[0.09584172822],"iteration":406,"passed_time":1.453381593,"remaining_time":2.117580552},
{"learn":[0.09576057492],"iteration":407,"passed_time":1.456277782,"remaining_time":2.113030507},
{"learn":[0.09568156164],"iteration":408,"passed_time":1.45925822,"remaining_time":2.108610288},
{"learn":[0.09557990385],"iteration":409,"passed_time":1.462377202,"remaining_time":2.104396462},
{"learn":[0.09552029086],"iteration":410,"passed_time":1.465535277,"remaining_time":2.100243986},
{"learn":[0.0954623257],"iteration":411,"passed_time":1.468747425,"remaining_time":2.096173509},
{"learn":[0.09536096779],"iteration":412,"passed_time":1.471908006,"remaining_time":2.092033898},
{"learn":[0.09526420172],"iteration":413,"passed_time":1.475010325,"remaining_time":2.087816547},
{"learn":[0.09513215304],"iteration":414,"passed_time":1.47802431,"remaining_time":2.083480052},
{"learn":[0.09500309712],"iteration":415,"passed_time":1.481180931,"remaining_time":2.079350153},
{"learn":[0.09498726258],"iteration":416,"passed_time":1.484175647,"remaining_time":2.074998566},
{"learn":[0.09489596368],"iteration":417,"passed_time":1.487313881,"remaining_time":2.070853298},
{"learn":[0.09479520149],"iteration":418,"passed_time":1.490132709,"remaining_time":2.066269937},
{"learn":[0.09465802825],"iteration":419,"passed_time":1.493130729,"remaining_time":2.061942435},
{"learn":[0.0945209158],"iteration":420,"passed_time":1.496154405,"remaining_time":2.057656533},
{"learn":[0.09445557111],"iteration":421,"passed_time":1.499350255,"remaining_time":2.053612435},
{"learn":[0.0944005621],"iteration":422,"passed_time":1.502610396,"remaining_time":2.049660044},
{"learn":[0.0942755712],"iteration":423,"passed_time":1.505610834,"remaining_time":2.045358114},
{"learn":[0.09415518468],"iteration":424,"passed_time":1.508818523,"remaining_time":2.041342708},
{"learn":[0.09406657713],"iteration":425,"passed_time":1.51177472,"remaining_time":2.036992228},
{"learn":[0.09400407673],"iteration":426,"passed_time":1.514780578,"remaining_time":2.032714921},
{"learn":[0.09390174188],"iteration":427,"passed_time":1.51762886,"remaining_time":2.028232963},
{"learn":[0.09382166567],"iteration":428,"passed_time":1.520485258,"remaining_time":2.023769422},
{"learn":[0.0937027388],"iteration":429,"passed_time":1.523483829,"remaining_time":2.01950182},
{"learn":[0.0936017104],"iteration":430,"passed_time":1.526381377,"remaining_time":2.015106736},
{"learn":[0.09349098604],"iteration":431,"passed_time":1.530238066,"remaining_time":2.01197968},
{"learn":[0.09343740747],"iteration":432,"passed_time":1.533929817,"remaining_time":2.008633271},
{"learn":[0.09330063572],"iteration":433,"passed_time":1.537527759,"remaining_time":2.00516293},
{"learn":[0.09319506842],"iteration":434,"passed_time":1.541079292,"remaining_time":2.001631725},
{"learn":[0.09309460799],"iteration":435,"passed_time":1.547014134,"remaining_time":2.00118342},
{"learn":[0.09299474298],"iteration":436,"passed_time":1.550195749,"remaining_time":1.997162944},
{"learn":[0.09286076163],"iteration":437,"passed_time":1.553343347,"remaining_time":1.993102651},
{"learn":[0.09279927456],"iteration":438,"passed_time":1.556758266,"remaining_time":1.989388126},
{"learn":[0.09270354978],"iteration":439,"passed_time":1.559768308,"remaining_time":1.985159664},
{"learn":[0.09262904459],"iteration":440,"passed_time":1.562786177,"remaining_time":1.980946651},
{"learn":[0.09250079039],"iteration":441,"passed_time":1.565988177,"remaining_time":1.976971499},
{"learn":[0.0923661416],"iteration":442,"passed_time":1.568887706,"remaining_time":1.97261953},
{"learn":[0.0923328444],"iteration":443,"passed_time":1.571839272,"remaining_time":1.968339269},
{"learn":[0.09221199339],"iteration":444,"passed_time":1.574703084,"remaining_time":1.963955531},
{"learn":[0.09213734478],"iteration":445,"passed_time":1.577592042,"remaining_time":1.959609846},
{"learn":[0.09200276411],"iteration":446,"passed_time":1.580496975,"remaining_time":1.955290441},
{"learn":[0.09192962716],"iteration":447,"passed_time":1.583424082,"remaining_time":1.951004672},
{"learn":[0.09186883308],"iteration":448,"passed_time":1.586282582,"remaining_time":1.946640764},
{"learn":[0.09180355652],"iteration":449,"passed_time":1.589177994,"remaining_time":1.942328659},
{"learn":[0.0917476047],"iteration":450,"passed_time":1.592383232,"remaining_time":1.938399987},
{"learn":[0.09165478773],"iteration":451,"passed_time":1.595471292,"remaining_time":1.934332451},
{"learn":[0.09157554713],"iteration":452,"passed_time":1.598471533,"remaining_time":1.930163197},
{"learn":[0.0914381933],"iteration":453,"passed_time":1.601523497,"remaining_time":1.926061298},
{"learn":[0.09139949705],"iteration":454,"passed_time":1.604314477,"remaining_time":1.921651406},
{"learn":[0.09130303992],"iteration":455,"passed_time":1.607409803,"remaining_time":1.917611695},
{"learn":[0.09120790207],"iteration":456,"passed_time":1.610527378,"remaining_time":1.913602552},
{"learn":[0.09109999592],"iteration":457,"passed_time":1.613528225,"remaining_time":1.909459166},
{"learn":[0.09100183114],"iteration":458,"passed_time":1.616558101,"remaining_time":1.905354974},
{"learn":[0.09093052025],"iteration":459,"passed_time":1.619479196,"remaining_time":1.901127751},
{"learn":[0.09083911612],"iteration":460,"passed_time":1.622516303,"remaining_time":1.897041838},
{"learn":[0.09081047884],"iteration":461,"passed_time":1.625503067,"remaining_time":1.89290184},
{"learn":[0.09075161755],"iteration":462,"passed_time":1.62856129,"remaining_time":1.888849703},
{"learn":[0.09069688871],"iteration":463,"passed_time":1.631584709,"remaining_time":1.884761646},
{"learn":[0.09061021031],"iteration":464,"passed_time":1.634730733,"remaining_time":1.880819231},
{"learn":[0.09053073197],"iteration":465,"passed_time":1.651388701,"remaining_time":1.892363876},
{"learn":[0.09047491356],"iteration":466,"passed_time":1.65408483,"remaining_time":1.887852707},
{"learn":[0.0903921401],"iteration":467,"passed_time":1.656892652,"remaining_time":1.883476263},
{"learn":[0.09031534465],"iteration":468,"passed_time":1.659856212,"remaining_time":1.879282833},
{"learn":[0.09025037696],"iteration":469,"passed_time":1.66282501,"remaining_time":1.875100543},
{"learn":[0.09019610328],"iteration":470,"passed_time":1.665677291,"remaining_time":1.870792541},
{"learn":[0.09012038461],"iteration":471,"passed_time":1.668650601,"remaining_time":1.866626096},
{"learn":[0.09002449872],"iteration":472,"passed_time":1.671366566,"remaining_time":1.862177971},
{"learn":[0.08993682127],"iteration":473,"passed_time":1.674117081,"remaining_time":1.857775495},
{"learn":[0.08987558646],"iteration":474,"passed_time":1.676970608,"remaining_time":1.853493829},
{"learn":[0.08977159628],"iteration":475,"passed_time":1.679667644,"remaining_time":1.849045894},
{"learn":[0.0896704054],"iteration":476,"passed_time":1.682418103,"remaining_time":1.844663874},
{"learn":[0.08955287872],"iteration":477,"passed_time":1.685223997,"remaining_time":1.840349219},
{"learn":[0.08943273486],"iteration":478,"passed_time":1.688095194,"remaining_time":1.836111892},
{"learn":[0.08935443127],"iteration":479,"passed_time":1.691034744,"remaining_time":1.831954306},
{"learn":[0.08928823143],"iteration":480,"passed_time":1.694279779,"remaining_time":1.828131403},
{"learn":[0.08923896373],"iteration":481,"passed_time":1.697448822,"remaining_time":1.824229232},
{"learn":[0.08917122314],"iteration":482,"passed_time":1.700478819,"remaining_time":1.820181262},
{"learn":[0.08907750377],"iteration":483,"passed_time":1.703411845,"remaining_time":1.816034115},
{"learn":[0.08897767671],"iteration":484,"passed_time":1.706252961,"remaining_time":1.811794381},
{"learn":[0.08891506928],"iteration":485,"passed_time":1.709116177,"remaining_time":1.807583776},
{"learn":[0.08886514502],"iteration":486,"passed_time":1.712257901,"remaining_time":1.803672081},
{"learn":[0.08880263041],"iteration":487,"passed_time":1.715632978,"remaining_time":1.80000837},
{"learn":[0.08871674684],"iteration":488,"passed_time":1.719259969,"remaining_time":1.796609088},
{"learn":[0.08861503091],"iteration":489,"passed_time":1.722149393,"remaining_time":1.792441205},
{"learn":[0.08853218363],"iteration":490,"passed_time":1.72504463,"remaining_time":1.788284555},
{"learn":[0.08844468523],"iteration":491,"passed_time":1.728021273,"remaining_time":1.784217087},
{"learn":[0.0883505883],"iteration":492,"passed_time":1.730932707,"remaining_time":1.780086983},
{"learn":[0.08830091074],"iteration":493,"passed_time":1.734060283,"remaining_time":1.776183205},
{"learn":[0.0881908991],"iteration":494,"passed_time":1.737166391,"remaining_time":1.772260662},
{"learn":[0.08809633784],"iteration":495,"passed_time":1.740353232,"remaining_time":1.768423446},
{"learn":[0.08806008042],"iteration":496,"passed_time":1.743556885,"remaining_time":1.764605861},
{"learn":[0.08800876184],"iteration":497,"passed_time":1.746527663,"remaining_time":1.760555998},
{"learn":[0.08790739014],"iteration":498,"passed_time":1.749578832,"remaining_time":1.756591172},
{"learn":[0.08782767027],"iteration":499,"passed_time":1.752670524,"remaining_time":1.752670524},
{"learn":[0.08774143474],"iteration":500,"passed_time":1.755782493,"remaining_time":1.748773382},
{"learn":[0.08766179197],"iteration":501,"passed_time":1.758878015,"remaining_time":1.744863051},
{"learn":[0.08759995838],"iteration":502,"passed_time":1.76183836,"remaining_time":1.740822395},
{"learn":[0.08746482067],"iteration":503,"passed_time":1.76497725,"remaining_time":1.736961738},
{"learn":[0.08735932762],"iteration":504,"passed_time":1.767930639,"remaining_time":1.732922111},
{"learn":[0.08729982114],"iteration":505,"passed_time":1.770840842,"remaining_time":1.728844616},
{"learn":[0.08723908789],"iteration":506,"passed_time":1.773837177,"remaining_time":1.724855479},
{"learn":[0.08716205082],"iteration":507,"passed_time":1.77681945,"remaining_time":1.720856633},
{"learn":[0.08704775544],"iteration":508,"passed_time":1.779708244,"remaining_time":1.716771607},
{"learn":[0.0869710157],"iteration":509,"passed_time":1.782527365,"remaining_time":1.712624331},
{"learn":[0.08688477421],"iteration":510,"passed_time":1.785504656,"remaining_time":1.708633614},
{"learn":[0.0868145887],"iteration":511,"passed_time":1.788504015,"remaining_time":1.704667889},
{"learn":[0.0867489095],"iteration":512,"passed_time":1.791750396,"remaining_time":1.700940435},
{"learn":[0.08667921388],"iteration":513,"passed_time":1.794830809,"remaining_time":1.697057924},
{"learn":[0.08663094735],"iteration":514,"passed_time":1.797923107,"remaining_time":1.693189722},
{"learn":[0.08652682705],"iteration":515,"passed_time":1.800960664,"remaining_time":1.689273181},
{"learn":[0.08641587168],"iteration":516,"passed_time":1.803948352,"remaining_time":1.685313451},
{"learn":[0.08636357702],"iteration":517,"passed_time":1.807514761,"remaining_time":1.681895975},
{"learn":[0.08628857033],"iteration":518,"passed_time":1.810509662,"remaining_time":1.677948261},
{"learn":[0.08625303105],"iteration":519,"passed_time":1.813512415,"remaining_time":1.67401146},
{"learn":[0.08615603102],"iteration":520,"passed_time":1.816673364,"remaining_time":1.670223688},
{"learn":[0.08611215517],"iteration":521,"passed_time":1.819830112,"remaining_time":1.666434471},
{"learn":[0.08606062308],"iteration":522,"passed_time":1.823115118,"remaining_time":1.662764648},
{"learn":[0.08601283825],"iteration":523,"passed_time":1.826252657,"remaining_time":1.658962337},
{"learn":[0.08596361117],"iteration":524,"passed_time":1.829156746,"remaining_time":1.654951342},
{"learn":[0.08592564045],"iteration":525,"passed_time":1.832241184,"remaining_time":1.651107074},
{"learn":[0.0858310916],"iteration":526,"passed_time":1.835147521,"remaining_time":1.64710584},
{"learn":[0.08574447254],"iteration":527,"passed_time":1.838061335,"remaining_time":1.643115436},
{"learn":[0.08563929535],"iteration":528,"passed_time":1.840956289,"remaining_time":1.639112311},
{"learn":[0.08562098481],"iteration":529,"passed_time":1.843798416,"remaining_time":1.63506652},
{"learn":[0.08550885592],"iteration":530,"passed_time":1.846762392,"remaining_time":1.631132885},
{"learn":[0.08544699111],"iteration":531,"passed_time":1.849550187,"remaining_time":1.627047909},
{"learn":[0.08536077431],"iteration":532,"passed_time":1.852387626,"remaining_time":1.623011297},
{"learn":[0.08529226105],"iteration":533,"passed_time":1.855818611,"remaining_time":1.61949714},
{"learn":[0.08522911347],"iteration":534,"passed_time":1.871376035,"remaining_time":1.626523096},
{"learn":[0.08515899117],"iteration":535,"passed_time":1.874619739,"remaining_time":1.622805147},
{"learn":[0.08503450672],"iteration":536,"passed_time":1.877427881,"remaining_time":1.618713425},
{"learn":[0.08494560338],"iteration":537,"passed_time":1.880162285,"remaining_time":1.614563152},
{"learn":[0.08489139445],"iteration":538,"passed_time":1.882985045,"remaining_time":1.610493703},
{"learn":[0.08477810184],"iteration":539,"passed_time":1.886025249,"remaining_time":1.606614101},
{"learn":[0.08472792432],"iteration":540,"passed_time":1.888912594,"remaining_time":1.602607913},
{"learn":[0.0846547502],"iteration":541,"passed_time":1.892183322,"remaining_time":1.598929818},
{"learn":[0.08460607067],"iteration":542,"passed_time":1.89514308,"remaining_time":1.594991506},
{"learn":[0.08457326891],"iteration":543,"passed_time":1.898021975,"remaining_time":1.590989008},
{"learn":[0.08452214443],"iteration":544,"passed_time":1.900814216,"remaining_time":1.58691829},
{"learn":[0.08442723793],"iteration":545,"passed_time":1.903571214,"remaining_time":1.582822951},
{"learn":[0.0843928886],"iteration":546,"passed_time":1.9063281,"remaining_time":1.578732412},
{"learn":[0.08431215633],"iteration":547,"passed_time":1.909132861,"remaining_time":1.574686228},
{"learn":[0.08428823735],"iteration":548,"passed_time":1.912102456,"remaining_time":1.570779978},
{"learn":[0.08419434359],"iteration":549,"passed_time":1.915199809,"remaining_time":1.566981662},
{"learn":[0.08411758514],"iteration":550,"passed_time":1.918271495,"remaining_time":1.563164975},
{"learn":[0.08402522762],"iteration":551,"passed_time":1.921264902,"remaining_time":1.559287456},
{"learn":[0.08393163838],"iteration":552,"passed_time":1.924213179,"remaining_time":1.555376656},
{"learn":[0.08391286247],"iteration":553,"passed_time":1.927018991,"remaining_time":1.551354639},
{"learn":[0.08388420164],"iteration":554,"passed_time":1.930106681,"remaining_time":1.547563015},
{"learn":[0.0837687423],"iteration":555,"passed_time":1.933209894,"remaining_time":1.543786318},
{"learn":[0.08368014733],"iteration":556,"passed_time":1.936202457,"remaining_time":1.539924037},
{"learn":[0.08357258185],"iteration":557,"passed_time":1.939218249,"remaining_time":1.536083273},
{"learn":[0.08351482126],"iteration":558,"passed_time":1.942264008,"remaining_time":1.532269101},
{"learn":[0.08347332224],"iteration":559,"passed_time":1.94522769,"remaining_time":1.528393185},
{"learn":[0.08339994387],"iteration":560,"passed_time":1.948641442,"remaining_time":1.524872715},
{"learn":[0.08332722792],"iteration":561,"passed_time":1.951813863,"remaining_time":1.521164541},
{"learn":[0.08327612803],"iteration":562,"passed_time":1.954900098,"remaining_time":1.517391372},
{"learn":[0.08320949554],"iteration":563,"passed_time":1.957994001,"remaining_time":1.513626568},
{"learn":[0.08315565926],"iteration":564,"passed_time":1.960900228,"remaining_time":1.509719644},
{"learn":[0.08307179463],"iteration":565,"passed_time":1.963906228,"remaining_time":1.505892762},
{"learn":[0.0829992631],"iteration":566,"passed_time":1.967100587,"remaining_time":1.502212617},
{"learn":[0.08293495301],"iteration":567,"passed_time":1.97005374,"remaining_time":1.498350732},
{"learn":[0.08281940095],"iteration":568,"passed_time":1.973115859,"remaining_time":1.494574579},
{"learn":[0.08279925681],"iteration":569,"passed_time":1.97600041,"remaining_time":1.490666976},
{"learn":[0.08276943229],"iteration":570,"passed_time":1.978927653,"remaining_time":1.486795032},
{"learn":[0.0826930208],"iteration":571,"passed_time":1.982179125,"remaining_time":1.483168996},
{"learn":[0.08262264972],"iteration":572,"passed_time":1.985351934,"remaining_time":1.479485647},
{"learn":[0.08251647565],"iteration":573,"passed_time":1.988442463,"remaining_time":1.475743013},
{"learn":[0.08245423203],"iteration":574,"passed_time":1.991625232,"remaining_time":1.472070823},
{"learn":[0.08237002684],"iteration":575,"passed_time":1.994752892,"remaining_time":1.468359768},
{"learn":[0.08228429291],"iteration":576,"passed_time":1.997850204,"remaining_time":1.464628486},
{"learn":[0.08218637643],"iteration":577,"passed_time":2.00096132,"remaining_time":1.460909476},
{"learn":[0.08213029349],"iteration":578,"passed_time":2.003858555,"remaining_time":1.457037049},
{"learn":[0.08207235342],"iteration":579,"passed_time":2.023619453,"remaining_time":1.465379604},
{"learn":[0.08198990025],"iteration":580,"passed_time":2.026634979,"remaining_time":1.46154915},
{"learn":[0.08192137996],"iteration":581,"passed_time":2.029503787,"remaining_time":1.457616122},
{"learn":[0.08186772955],"iteration":582,"passed_time":2.032217908,"remaining_time":1.453576102},
{"learn":[0.08181484064],"iteration":583,"passed_time":2.03482382,"remaining_time":1.449463543},
{"learn":[0.08169813098],"iteration":584,"passed_time":2.037472051,"remaining_time":1.445386156},
{"learn":[0.08160035705],"iteration":585,"passed_time":2.040231672,"remaining_time":1.441392342},
{"learn":[0.08152192117],"iteration":586,"passed_time":2.042872736,"remaining_time":1.437319318},
{"learn":[0.0814238193],"iteration":587,"passed_time":2.045589168,"remaining_time":1.433303975},
{"learn":[0.08136922035],"iteration":588,"passed_time":2.048325198,"remaining_time":1.429306717},
{"learn":[0.08127340881],"iteration":589,"passed_time":2.05118937,"remaining_time":1.425402783},
{"learn":[0.08119429833],"iteration":590,"passed_time":2.054084982,"remaining_time":1.421524125},
{"learn":[0.08116334102],"iteration":591,"passed_time":2.057018164,"remaining_time":1.417674681},
{"learn":[0.08107535379],"iteration":592,"passed_time":2.059934661,"remaining_time":1.413816875},
{"learn":[0.08103062841],"iteration":593,"passed_time":2.06267049,"remaining_time":1.409838752},
{"learn":[0.08095500799],"iteration":594,"passed_time":2.06555855,"remaining_time":1.405968425},
{"learn":[0.08086351716],"iteration":595,"passed_time":2.068476857,"remaining_time":1.402121896},
{"learn":[0.08081668203],"iteration":596,"passed_time":2.071307062,"remaining_time":1.398219005},
{"learn":[0.0807742917],"iteration":597,"passed_time":2.074361757,"remaining_time":1.394470613},
{"learn":[0.08069173319],"iteration":598,"passed_time":2.077466976,"remaining_time":1.39075836},
{"learn":[0.08058545405],"iteration":599,"passed_time":2.080446521,"remaining_time":1.386964347},
{"learn":[0.08047718158],"iteration":600,"passed_time":2.083442203,"remaining_time":1.383183759},
{"learn":[0.08038396356],"iteration":601,"passed_time":2.086289232,"remaining_time":1.379307499},
{"learn":[0.08032247665],"iteration":602,"passed_time":2.089105376,"remaining_time":1.375414319},
{"learn":[0.08027163521],"iteration":603,"passed_time":2.09198273,"remaining_time":1.371564836},
{"learn":[0.08024343788],"iteration":604,"passed_time":2.094747078,"remaining_time":1.367644787},
{"learn":[0.08019047474],"iteration":605,"passed_time":2.097558376,"remaining_time":1.363759076},
{"learn":[0.08008082812],"iteration":606,"passed_time":2.100532946,"remaining_time":1.359982616},
{"learn":[0.08001377581],"iteration":607,"passed_time":2.103411552,"remaining_time":1.356146922},
{"learn":[0.07997751378],"iteration":608,"passed_time":2.106425379,"remaining_time":1.352401187},
{"learn":[0.0799164477],"iteration":609,"passed_time":2.109458659,"remaining_time":1.34867029},
{"learn":[0.07985419288],"iteration":610,"passed_time":2.112581219,"remaining_time":1.344998518},
{"learn":[0.07976330865],"iteration":611,"passed_time":2.115525674,"remaining_time":1.341215623},
{"learn":[0.07970739776],"iteration":612,"passed_time":2.118438111,"remaining_time":1.337415251},
{"learn":[0.07962990908],"iteration":613,"passed_time":2.121509398,"remaining_time":1.333717635},
{"learn":[0.07957489074],"iteration":614,"passed_time":2.124453445,"remaining_time":1.329942401},
{"learn":[0.07952448412],"iteration":615,"passed_time":2.127378583,"remaining_time":1.326158078},
{"learn":[0.07948213092],"iteration":616,"passed_time":2.130246209,"remaining_time":1.32234084},
{"learn":[0.07942677838],"iteration":617,"passed_time":2.133102274,"remaining_time":1.318519529},
{"learn":[0.07936314308],"iteration":618,"passed_time":2.135949605,"remaining_time":1.31469596},
{"learn":[0.07926041697],"iteration":619,"passed_time":2.138896742,"remaining_time":1.310936713},
{"learn":[0.07920661191],"iteration":620,"passed_time":2.141872426,"remaining_time":1.307197503},
{"learn":[0.07913167221],"iteration":621,"passed_time":2.1449125,"remaining_time":1.303499879},
{"learn":[0.07905345302],"iteration":622,"passed_time":2.147854862,"remaining_time":1.299745237},
{"learn":[0.07901242452],"iteration":623,"passed_time":2.150745533,"remaining_time":1.295962052},
{"learn":[0.07894912988],"iteration":624,"passed_time":2.153712793,"remaining_time":1.292227676},
{"learn":[0.07887880192],"iteration":625,"passed_time":2.156757356,"remaining_time":1.288541935},
{"learn":[0.07877754891],"iteration":626,"passed_time":2.15963281,"remaining_time":1.284757637},
{"learn":[0.07872234992],"iteration":627,"passed_time":2.16258972,"remaining_time":1.281024484},
{"learn":[0.07865282187],"iteration":628,"passed_time":2.16552136,"remaining_time":1.277278894},
{"learn":[0.07860576417],"iteration":629,"passed_time":2.168525051,"remaining_time":1.273578205},
{"learn":[0.07853268286],"iteration":630,"passed_time":2.171496098,"remaining_time":1.269860634},
{"learn":[0.07845511993],"iteration":631,"passed_time":2.174492192,"remaining_time":1.266160011},
{"learn":[0.07843030963],"iteration":632,"passed_time":2.177934185,"remaining_time":1.262720136},
{"learn":[0.07835426828],"iteration":633,"passed_time":2.181196182,"remaining_time":1.259176345},
{"learn":[0.07830006704],"iteration":634,"passed_time":2.18420208,"remaining_time":1.255486235},
{"learn":[0.07821926675],"iteration":635,"passed_time":2.187162987,"remaining_time":1.251772527},
{"learn":[0.07819532909],"iteration":636,"passed_time":2.189955269,"remaining_time":1.247965091},
{"learn":[0.07810208627],"iteration":637,"passed_time":2.192912616,"remaining_time":1.244254494},
{"learn":[0.07799552242],"iteration":638,"passed_time":2.195862919,"remaining_time":1.240542275},
{"learn":[0.07792874272],"iteration":639,"passed_time":2.198699055,"remaining_time":1.236768219},
{"learn":[0.07783940472],"iteration":640,"passed_time":2.201758654,"remaining_time":1.233122242},
{"learn":[0.07772684253],"iteration":641,"passed_time":2.204604643,"remaining_time":1.229358975},
{"learn":[0.07766537409],"iteration":642,"passed_time":2.207633307,"remaining_time":1.225699985},
{"learn":[0.07755870491],"iteration":643,"passed_time":2.210779943,"remaining_time":1.222108167},
{"learn":[0.07751896363],"iteration":644,"passed_time":2.214168297,"remaining_time":1.218650768},
{"learn":[0.07741433105],"iteration":645,"passed_time":2.217217394,"remaining_time":1.215007674},
{"learn":[0.0773743349],"iteration":646,"passed_time":2.220205554,"remaining_time":1.211333169},
{"learn":[0.07733478592],"iteration":647,"passed_time":2.223146958,"remaining_time":1.207635385},
{"learn":[0.07729497692],"iteration":648,"passed_time":2.226078108,"remaining_time":1.203934385},
{"learn":[0.07722044721],"iteration":649,"passed_time":2.228982008,"remaining_time":1.200221081},
{"learn":[0.07720372733],"iteration":650,"passed_time":2.231850326,"remaining_time":1.196491189},
{"learn":[0.07718398662],"iteration":651,"passed_time":2.234877278,"remaining_time":1.192848608},
{"learn":[0.0770971756],"iteration":652,"passed_time":2.238325775,"remaining_time":1.189431921},
{"learn":[0.07703197927],"iteration":653,"passed_time":2.241578578,"remaining_time":1.185911603},
{"learn":[0.07698520621],"iteration":654,"passed_time":2.244613229,"remaining_time":1.182277197},
{"learn":[0.07693335728],"iteration":655,"passed_time":2.247471294,"remaining_time":1.17855202},
{"learn":[0.07691776419],"iteration":656,"passed_time":2.250477976,"remaining_time":1.174907071},
{"learn":[0.07682273739],"iteration":657,"passed_time":2.253658903,"remaining_time":1.171354627},
{"learn":[0.07680407885],"iteration":658,"passed_time":2.256596516,"remaining_time":1.167677408},
{"learn":[0.07675223618],"iteration":659,"passed_time":2.25955858,"remaining_time":1.164015026},
{"learn":[0.07669636959],"iteration":660,"passed_time":2.262491628,"remaining_time":1.160339882},
{"learn":[0.07665485206],"iteration":661,"passed_time":2.265248938,"remaining_time":1.156577252},
{"learn":[0.07655532628],"iteration":662,"passed_time":2.268061035,"remaining_time":1.152845503},
{"learn":[0.07653024364],"iteration":663,"passed_time":2.27110667,"remaining_time":1.149234701},
{"learn":[0.07648561871],"iteration":664,"passed_time":2.274088834,"remaining_time":1.145593623},
{"learn":[0.07644211277],"iteration":665,"passed_time":2.27694365,"remaining_time":1.141890659},
{"learn":[0.07636971241],"iteration":666,"passed_time":2.280054774,"remaining_time":1.1383182},
{"learn":[0.07626241183],"iteration":667,"passed_time":2.283107562,"remaining_time":1.13471813},
{"learn":[0.07619876439],"iteration":668,"passed_time":2.286101388,"remaining_time":1.131090522},
{"learn":[0.07615597791],"iteration":669,"passed_time":2.289089008,"remaining_time":1.12746175},
{"learn":[0.07605627887],"iteration":670,"passed_time":2.292263122,"remaining_time":1.12392633},
{"learn":[0.07599510632],"iteration":671,"passed_time":2.295459844,"remaining_time":1.120403019},
{"learn":[0.07594053983],"iteration":672,"passed_time":2.298309116,"remaining_time":1.116711859},
{"learn":[0.0758017189],"iteration":673,"passed_time":2.301378547,"remaining_time":1.113129683},
{"learn":[0.07570679248],"iteration":674,"passed_time":2.304524586,"remaining_time":1.109585912},
{"learn":[0.07564620282],"iteration":675,"passed_time":2.307666153,"remaining_time":1.106041174},
{"learn":[0.07557122745],"iteration":676,"passed_time":2.310759345,"remaining_time":1.102474547},
{"learn":[0.07549040845],"iteration":677,"passed_time":2.313766988,"remaining_time":1.098868688},
{"learn":[0.07541904188],"iteration":678,"passed_time":2.316663143,"remaining_time":1.095211884},
{"learn":[0.07538392497],"iteration":679,"passed_time":2.31949765,"remaining_time":1.091528306},
{"learn":[0.07530058664],"iteration":680,"passed_time":2.32239052,"remaining_time":1.087874561},
{"learn":[0.07526332176],"iteration":681,"passed_time":2.325209371,"remaining_time":1.084188534},
{"learn":[0.07523463019],"iteration":682,"passed_time":2.328051052,"remaining_time":1.080515642},
{"learn":[0.07519962473],"iteration":683,"passed_time":2.331027679,"remaining_time":1.076907524},
{"learn":[0.07508745251],"iteration":684,"passed_time":2.333930978,"remaining_time":1.07326753},
{"learn":[0.07503456972],"iteration":685,"passed_time":2.336815537,"remaining_time":1.069621106},
{"learn":[0.07495000556],"iteration":686,"passed_time":2.339954514,"remaining_time":1.066092814},
{"learn":[0.07490727978],"iteration":687,"passed_time":2.34316606,"remaining_time":1.062598562},
{"learn":[0.07486656701],"iteration":688,"passed_time":2.346390928,"remaining_time":1.059111144},
{"learn":[0.07479601752],"iteration":689,"passed_time":2.34945692,"remaining_time":1.055553109},
{"learn":[0.07470453887],"iteration":690,"passed_time":2.352316373,"remaining_time":1.051904138},
{"learn":[0.07457579557],"iteration":691,"passed_time":2.355250199,"remaining_time":1.048290551},
{"learn":[0.07452785863],"iteration":692,"passed_time":2.358250714,"remaining_time":1.044708469},
{"learn":[0.07448366692],"iteration":693,"passed_time":2.361167058,"remaining_time":1.041090951},
{"learn":[0.07441527167],"iteration":694,"passed_time":2.364060942,"remaining_time":1.037465593},
{"learn":[0.07438118728],"iteration":695,"passed_time":2.366944354,"remaining_time":1.033837764},
{"learn":[0.07436943832],"iteration":696,"passed_time":2.370032746,"remaining_time":1.03030118},
{"learn":[0.07429848653],"iteration":697,"passed_time":2.373107098,"remaining_time":1.026759805},
{"learn":[0.07427344107],"iteration":698,"passed_time":2.376269843,"remaining_time":1.023257829},
{"learn":[0.0742307969],"iteration":699,"passed_time":2.379651433,"remaining_time":1.019850614},
{"learn":[0.07415405837],"iteration":700,"passed_time":2.382989282,"remaining_time":1.016424815},
{"learn":[0.07402944898],"iteration":701,"passed_time":2.386160502,"remaining_time":1.012928532},
{"learn":[0.07397826855],"iteration":702,"passed_time":2.389267759,"remaining_time":1.009406151},
{"learn":[0.07394988036],"iteration":703,"passed_time":2.392858469,"remaining_time":1.00608822},
{"learn":[0.0739362619],"iteration":704,"passed_time":2.395912938,"remaining_time":1.00254513},
{"learn":[0.0738135354],"iteration":705,"passed_time":2.399267967,"remaining_time":0.999128587},
{"learn":[0.07374756035],"iteration":706,"passed_time":2.402586598,"remaining_time":0.9956971331},
{"learn":[0.07369624253],"iteration":707,"passed_time":2.405667312,"remaining_time":0.9921678744},
{"learn":[0.07361232861],"iteration":708,"passed_time":2.408698242,"remaining_time":0.9886194476},
{"learn":[0.0735410549],"iteration":709,"passed_time":2.41152589,"remaining_time":0.9849894478},
{"learn":[0.0734945492],"iteration":710,"passed_time":2.414369457,"remaining_time":0.9813681759},
{"learn":[0.07343777911],"iteration":711,"passed_time":2.417187649,"remaining_time":0.9777388244},
{"learn":[0.07339328909],"iteration":712,"passed_time":2.420036944,"remaining_time":0.9741242679},
{"learn":[0.07332710979],"iteration":713,"passed_time":2.423054557,"remaining_time":0.9705792763},
{"learn":[0.07328529996],"iteration":714,"passed_time":2.426075034,"remaining_time":0.9670369018},
{"learn":[0.07324739134],"iteration":715,"passed_time":2.428986823,"remaining_time":0.9634528741},
{"learn":[0.07317639595],"iteration":716,"passed_time":2.432155179,"remaining_time":0.9599719883},
{"learn":[0.07311469841],"iteration":717,"passed_time":2.435240827,"remaining_time":0.9564594892},
{"learn":[0.07310844633],"iteration":718,"passed_time":2.438297818,"remaining_time":0.9529369777},
{"learn":[0.07305899283],"iteration":719,"passed_time":2.441276445,"remaining_time":0.9493852843},
{"learn":[0.07300263022],"iteration":720,"passed_time":2.444211663,"remaining_time":0.9458183829},
{"learn":[0.07291188218],"iteration":721,"passed_time":2.447250393,"remaining_time":0.9422930876},
{"learn":[0.07282711378],"iteration":722,"passed_time":2.450251229,"remaining_time":0.9387546201},
{"learn":[0.07279403347],"iteration":723,"passed_time":2.453382972,"remaining_time":0.9352675419},
{"learn":[0.07273421767],"iteration":724,"passed_time":2.456600021,"remaining_time":0.931813801},
{"learn":[0.07267328775],"iteration":725,"passed_time":2.459420312,"remaining_time":0.9282109719},
{"learn":[0.07263348491],"iteration":726,"passed_time":2.462219381,"remaining_time":0.9246023262},
{"learn":[0.07258510231],"iteration":727,"passed_time":2.464995298,"remaining_time":0.9209872543},
{"learn":[0.07249835315],"iteration":728,"passed_time":2.468128853,"remaining_time":0.9175074339},
{"learn":[0.07246021556],"iteration":729,"passed_time":2.471209269,"remaining_time":0.9140089076},
{"learn":[0.07242313014],"iteration":730,"passed_time":2.474056746,"remaining_time":0.9104258067},
{"learn":[0.07238046746],"iteration":731,"passed_time":2.477021304,"remaining_time":0.9068875811},
{"learn":[0.07232978838],"iteration":732,"passed_time":2.479910754,"remaining_time":0.9033235625},
{"learn":[0.07228244589],"iteration":733,"passed_time":2.482796923,"remaining_time":0.8997601927},
{"learn":[0.07222134264],"iteration":734,"passed_time":2.48567014,"remaining_time":0.8961939959},
{"learn":[0.07210375907],"iteration":735,"passed_time":2.488521382,"remaining_time":0.8926218002},
{"learn":[0.07209281484],"iteration":736,"passed_time":2.491267362,"remaining_time":0.8890139975},
{"learn":[0.07202710613],"iteration":737,"passed_time":2.494254787,"remaining_time":0.8854942469},
{"learn":[0.07201423053],"iteration":738,"passed_time":2.497131642,"remaining_time":0.8819368857},
{"learn":[0.07191631422],"iteration":739,"passed_time":2.500526527,"remaining_time":0.8785633743},
{"learn":[0.07187060598],"iteration":740,"passed_time":2.503595206,"remaining_time":0.8750757874},
{"learn":[0.07179733893],"iteration":741,"passed_time":2.506721354,"remaining_time":0.8716093118},
{"learn":[0.0717031987],"iteration":742,"passed_time":2.509902352,"remaining_time":0.8681627246},
{"learn":[0.07164567933],"iteration":743,"passed_time":2.512818502,"remaining_time":0.8646257211},
{"learn":[0.07154084867],"iteration":744,"passed_time":2.515760186,"remaining_time":0.8610991241},
{"learn":[0.07151416281],"iteration":745,"passed_time":2.518607072,"remaining_time":0.857541818},
{"learn":[0.07136367345],"iteration":746,"passed_time":2.521485492,"remaining_time":0.8539970945},
{"learn":[0.07133228303],"iteration":747,"passed_time":2.52435346,"remaining_time":0.8504506309},
{"learn":[0.07129330348],"iteration":748,"passed_time":2.527200705,"remaining_time":0.8468990346},
{"learn":[0.07126052029],"iteration":749,"passed_time":2.530056674,"remaining_time":0.8433522248},
{"learn":[0.07122187498],"iteration":750,"passed_time":2.532958211,"remaining_time":0.8398223628},
{"learn":[0.07115013694],"iteration":751,"passed_time":2.536194987,"remaining_time":0.8364047296},
{"learn":[0.07113087939],"iteration":752,"passed_time":2.539182814,"remaining_time":0.8329059163},
{"learn":[0.07101555627],"iteration":753,"passed_time":2.542141478,"remaining_time":0.8293989439},
{"learn":[0.0709763775],"iteration":754,"passed_time":2.545061189,"remaining_time":0.8258807833},
{"learn":[0.07094610134],"iteration":755,"passed_time":2.547914905,"remaining_time":0.8223429057},
{"learn":[0.07088449655],"iteration":756,"passed_time":2.551024871,"remaining_time":0.8188890933},
{"learn":[0.07082403089],"iteration":757,"passed_time":2.553851067,"remaining_time":0.8153455913},
{"learn":[0.0707881031],"iteration":758,"passed_time":2.556892739,"remaining_time":0.811872398},
{"learn":[0.07075137677],"iteration":759,"passed_time":2.559817794,"remaining_time":0.8083635138},
{"learn":[0.07064158155],"iteration":760,"passed_time":2.563003828,"remaining_time":0.8049381272},
{"learn":[0.07060194573],"iteration":761,"passed_time":2.566075226,"remaining_time":0.8014775639},
{"learn":[0.07056455706],"iteration":762,"passed_time":2.568975722,"remaining_time":0.797964936},
{"learn":[0.07049847691],"iteration":763,"passed_time":2.571925067,"remaining_time":0.7944689996},
{"learn":[0.07046712968],"iteration":764,"passed_time":2.574813764,"remaining_time":0.7909558621},
{"learn":[0.07043682129],"iteration":765,"passed_time":2.57786057,"remaining_time":0.7874926546},
{"learn":[0.07037946926],"iteration":766,"passed_time":2.580724262,"remaining_time":0.7839749063},
{"learn":[0.0703112473],"iteration":767,"passed_time":2.583506031,"remaining_time":0.7804341136},
{"learn":[0.07027959053],"iteration":768,"passed_time":2.59851648,"remaining_time":0.7805686696},
{"learn":[0.07019118241],"iteration":769,"passed_time":2.605140712,"remaining_time":0.778158914},
{"learn":[0.07015409083],"iteration":770,"passed_time":2.610664444,"remaining_time":0.7754113589},
{"learn":[0.0701026381],"iteration":771,"passed_time":2.615418867,"remaining_time":0.7724294064},
{"learn":[0.07001798735],"iteration":772,"passed_time":2.61973065,"remaining_time":0.7693128817},
{"learn":[0.06998363805],"iteration":773,"passed_time":2.623577073,"remaining_time":0.7660573883},
{"learn":[0.0698920111],"iteration":774,"passed_time":2.626997309,"remaining_time":0.7626766381},
{"learn":[0.06982344865],"iteration":775,"passed_time":2.63046318,"remaining_time":0.7593089593},
{"learn":[0.06975965268],"iteration":776,"passed_time":2.633572717,"remaining_time":0.7558387593},
{"learn":[0.06971905759],"iteration":777,"passed_time":2.636621378,"remaining_time":0.7523521155},
{"learn":[0.06966285067],"iteration":778,"passed_time":2.639381697,"remaining_time":0.7487847948},
{"learn":[0.06957610135],"iteration":779,"passed_time":2.642163212,"remaining_time":0.7452255212},
{"learn":[0.06947745343],"iteration":780,"passed_time":2.64488358,"remaining_time":0.7416510936},
{"learn":[0.06942183465],"iteration":781,"passed_time":2.647543866,"remaining_time":0.7380621007},
{"learn":[0.06932895112],"iteration":782,"passed_time":2.650253181,"remaining_time":0.7344890681},
{"learn":[0.06924643615],"iteration":783,"passed_time":2.65297811,"remaining_time":0.7309225406},
{"learn":[0.06921319486],"iteration":784,"passed_time":2.655727382,"remaining_time":0.7273648244},
{"learn":[0.06918428659],"iteration":785,"passed_time":2.658526072,"remaining_time":0.7238226202},
{"learn":[0.06907234954],"iteration":786,"passed_time":2.661619215,"remaining_time":0.7203619986},
{"learn":[0.06899574615],"iteration":787,"passed_time":2.66459254,"remaining_time":0.7168700741},
{"learn":[0.06893495853],"iteration":788,"passed_time":2.667422737,"remaining_time":0.7133411883},
{"learn":[0.06891786752],"iteration":789,"passed_time":2.670275413,"remaining_time":0.7098200466},
{"learn":[0.06887125538],"iteration":790,"passed_time":2.673285779,"remaining_time":0.7063422602},
{"learn":[0.06883389769],"iteration":791,"passed_time":2.676309179,"remaining_time":0.7028690774},
{"learn":[0.06879202722],"iteration":792,"passed_time":2.67972464,"remaining_time":0.6994993702},
{"learn":[0.06875088107],"iteration":793,"passed_time":2.682529912,"remaining_time":0.6959712366},
{"learn":[0.06871247724],"iteration":794,"passed_time":2.685441744,"remaining_time":0.6924723993},
{"learn":[0.06866183533],"iteration":795,"passed_time":2.68822534,"remaining_time":0.6889421725},
{"learn":[0.06857725283],"iteration":796,"passed_time":2.690961382,"remaining_time":0.685401707},
{"learn":[0.06854934115],"iteration":797,"passed_time":2.694038325,"remaining_time":0.6819495508},
{"learn":[0.06851226821],"iteration":798,"passed_time":2.696987142,"remaining_time":0.6784661021},
{"learn":[0.06847072475],"iteration":799,"passed_time":2.70013776,"remaining_time":0.67503444},
{"learn":[0.06840432887],"iteration":800,"passed_time":2.703121585,"remaining_time":0.6715620417},
{"learn":[0.06837428793],"iteration":801,"passed_time":2.705992801,"remaining_time":0.6680630607},
{"learn":[0.06830199793],"iteration":802,"passed_time":2.708915499,"remaining_time":0.664578273},
{"learn":[0.06822636633],"iteration":803,"passed_time":2.711990865,"remaining_time":0.6611321014},
{"learn":[0.06820109806],"iteration":804,"passed_time":2.714981466,"remaining_time":0.6576663178},
{"learn":[0.06817629398],"iteration":805,"passed_time":2.717959333,"remaining_time":0.6541986484},
{"learn":[0.06808178856],"iteration":806,"passed_time":2.720970039,"remaining_time":0.6507400466},
{"learn":[0.06805069527],"iteration":807,"passed_time":2.724253609,"remaining_time":0.6473473922},
{"learn":[0.06797603546],"iteration":808,"passed_time":2.72735007,"remaining_time":0.6439108324},
{"learn":[0.06790187716],"iteration":809,"passed_time":2.730456225,"remaining_time":0.640477386},
{"learn":[0.0678574812],"iteration":810,"passed_time":2.733292899,"remaining_time":0.6369819457},
{"learn":[0.0677914568],"iteration":811,"passed_time":2.736243009,"remaining_time":0.6335143913},
{"learn":[0.06770486848],"iteration":812,"passed_time":2.739106774,"remaining_time":0.6300282494},
{"learn":[0.06765530376],"iteration":813,"passed_time":2.74198606,"remaining_time":0.6265471833},
{"learn":[0.06756689564],"iteration":814,"passed_time":2.744995424,"remaining_time":0.6230971207},
{"learn":[0.0674951329],"iteration":815,"passed_time":2.747803269,"remaining_time":0.619602698},
{"learn":[0.06744579708],"iteration":816,"passed_time":2.750602843,"remaining_time":0.6161081031},
{"learn":[0.06738239105],"iteration":817,"passed_time":2.753384571,"remaining_time":0.6126112371},
{"learn":[0.06732345444],"iteration":818,"passed_time":2.756380809,"remaining_time":0.6091635244},
{"learn":[0.06724711716],"iteration":819,"passed_time":2.759413863,"remaining_time":0.6057249943},
{"learn":[0.06717105222],"iteration":820,"passed_time":2.762450784,"remaining_time":0.6022882952},
{"learn":[0.06707850293],"iteration":821,"passed_time":2.765327774,"remaining_time":0.5988179365},
{"learn":[0.06702701915],"iteration":822,"passed_time":2.768091347,"remaining_time":0.5953246275},
{"learn":[0.06699432266],"iteration":823,"passed_time":2.77087006,"remaining_time":0.5918363236},
{"learn":[0.06688769176],"iteration":824,"passed_time":2.77378387,"remaining_time":0.5883783967},
{"learn":[0.06684432956],"iteration":825,"passed_time":2.776769083,"remaining_time":0.5849368286},
{"learn":[0.06680520038],"iteration":826,"passed_time":2.779644519,"remaining_time":0.5814733999},
{"learn":[0.06673948648],"iteration":827,"passed_time":2.782478564,"remaining_time":0.5780027936},
{"learn":[0.06670688911],"iteration":828,"passed_time":2.785249431,"remaining_time":0.5745206908},
{"learn":[0.06667999777],"iteration":829,"passed_time":2.788304325,"remaining_time":0.5710984763},
{"learn":[0.06666745028],"iteration":830,"passed_time":2.791378897,"remaining_time":0.5676811475},
{"learn":[0.06658582036],"iteration":831,"passed_time":2.794415977,"remaining_time":0.5642570723},
{"learn":[0.06651605709],"iteration":832,"passed_time":2.797302267,"remaining_time":0.5608036959},
{"learn":[0.06646526045],"iteration":833,"passed_time":2.800239456,"remaining_time":0.5573618102},
{"learn":[0.06638182304],"iteration":834,"passed_time":2.803091096,"remaining_time":0.5539042286},
{"learn":[0.06634927509],"iteration":835,"passed_time":2.805926768,"remaining_time":0.550444964},
{"learn":[0.06633417724],"iteration":836,"passed_time":2.808670974,"remaining_time":0.5469693772},
{"learn":[0.06630018082],"iteration":837,"passed_time":2.8116567,"remaining_time":0.543542226},
{"learn":[0.06624877758],"iteration":838,"passed_time":2.814590469,"remaining_time":0.5401061568},
{"learn":[0.06621781427],"iteration":839,"passed_time":2.817503711,"remaining_time":0.5366673735},
{"learn":[0.06618662812],"iteration":840,"passed_time":2.820718111,"remaining_time":0.5332867772},
{"learn":[0.06616404635],"iteration":841,"passed_time":2.823905303,"remaining_time":0.5299014702},
{"learn":[0.06611752091],"iteration":842,"passed_time":2.82692721,"remaining_time":0.5264858505},
{"learn":[0.06609077311],"iteration":843,"passed_time":2.830012599,"remaining_time":0.5230828975},
{"learn":[0.06601403361],"iteration":844,"passed_time":2.833070285,"remaining_time":0.5196756144},
{"learn":[0.06592856077],"iteration":845,"passed_time":2.836059584,"remaining_time":0.5162567091},
{"learn":[0.06590332833],"iteration":846,"passed_time":2.83893509,"remaining_time":0.512818263},
{"learn":[0.06583554591],"iteration":847,"passed_time":2.84186833,"remaining_time":0.5093914932},
{"learn":[0.06579273464],"iteration":848,"passed_time":2.844670024,"remaining_time":0.5059424895},
{"learn":[0.0657390658],"iteration":849,"passed_time":2.847485281,"remaining_time":0.5024974025},
{"learn":[0.06568113814],"iteration":850,"passed_time":2.850380061,"remaining_time":0.4990677193},
{"learn":[0.06563871053],"iteration":851,"passed_time":2.853446628,"remaining_time":0.4956691325},
{"learn":[0.06556808679],"iteration":852,"passed_time":2.856506864,"remaining_time":0.4922702332},
{"learn":[0.06553326704],"iteration":853,"passed_time":2.859506272,"remaining_time":0.488861728},
{"learn":[0.06547164385],"iteration":854,"passed_time":2.862576182,"remaining_time":0.4854661361},
{"learn":[0.06540073539],"iteration":855,"passed_time":2.865580792,"remaining_time":0.4820603202},
{"learn":[0.06531406671],"iteration":856,"passed_time":2.868585431,"remaining_time":0.4786554454},
{"learn":[0.06529149113],"iteration":857,"passed_time":2.871515415,"remaining_time":0.4752391479},
{"learn":[0.06525171301],"iteration":858,"passed_time":2.874320969,"remaining_time":0.4718035584},
{"learn":[0.06522307721],"iteration":859,"passed_time":2.877148203,"remaining_time":0.4683729633},
{"learn":[0.06515504096],"iteration":860,"passed_time":2.880378956,"remaining_time":0.465008914},
{"learn":[0.06507549095],"iteration":861,"passed_time":2.884351133,"remaining_time":0.4617638704},
{"learn":[0.06499234448],"iteration":862,"passed_time":2.88775461,"remaining_time":0.4584268616},
{"learn":[0.06491836556],"iteration":863,"passed_time":2.890719518,"remaining_time":0.4550206649},
{"learn":[0.06488234488],"iteration":864,"passed_time":2.893625062,"remaining_time":0.4516062235},
{"learn":[0.06482768561],"iteration":865,"passed_time":2.896441845,"remaining_time":0.4481792232},
{"learn":[0.06478272008],"iteration":866,"passed_time":2.89928764,"remaining_time":0.4447580809},
{"learn":[0.06474419242],"iteration":867,"passed_time":2.902126351,"remaining_time":0.4413371871},
{"learn":[0.06467775939],"iteration":868,"passed_time":2.904993597,"remaining_time":0.4379219346},
{"learn":[0.06464231443],"iteration":869,"passed_time":2.907754885,"remaining_time":0.4344921093},
{"learn":[0.06456202785],"iteration":870,"passed_time":2.910594925,"remaining_time":0.4310754825},
{"learn":[0.06454037953],"iteration":871,"passed_time":2.913428253,"remaining_time":0.427659193},
{"learn":[0.06452027487],"iteration":872,"passed_time":2.916373144,"remaining_time":0.4242604689},
{"learn":[0.0644572279],"iteration":873,"passed_time":2.91952153,"remaining_time":0.4208921199},
{"learn":[0.06438103815],"iteration":874,"passed_time":2.922647423,"remaining_time":0.4175210604},
{"learn":[0.06433573843],"iteration":875,"passed_time":2.925733318,"remaining_time":0.4141448988},
{"learn":[0.06427290809],"iteration":876,"passed_time":2.92880497,"remaining_time":0.4107674017},
{"learn":[0.06425415081],"iteration":877,"passed_time":2.931894212,"remaining_time":0.4073930454},
{"learn":[0.06420979815],"iteration":878,"passed_time":2.934803731,"remaining_time":0.4039945978},
{"learn":[0.06417815399],"iteration":879,"passed_time":2.93774384,"remaining_time":0.4006014327},
{"learn":[0.06416689402],"iteration":880,"passed_time":2.940616553,"remaining_time":0.3972001928},
{"learn":[0.06414148445],"iteration":881,"passed_time":2.943558448,"remaining_time":0.3938094069},
{"learn":[0.06408120951],"iteration":882,"passed_time":2.946893537,"remaining_time":0.390471737},
{"learn":[0.06407376273],"iteration":883,"passed_time":2.950739203,"remaining_time":0.3872010719},
{"learn":[0.06404324515],"iteration":884,"passed_time":2.954002058,"remaining_time":0.3838533747},
{"learn":[0.06400334942],"iteration":885,"passed_time":2.957086072,"remaining_time":0.380482858},
{"learn":[0.06393089957],"iteration":886,"passed_time":2.960551961,"remaining_time":0.3771616365},
{"learn":[0.06384535131],"iteration":887,"passed_time":2.9635437,"remaining_time":0.3737802865},
{"learn":[0.06381337901],"iteration":888,"passed_time":2.966738295,"remaining_time":0.3704251414},
{"learn":[0.06375318575],"iteration":889,"passed_time":2.969890217,"remaining_time":0.3670650831},
{"learn":[0.06366893127],"iteration":890,"passed_time":2.97325598,"remaining_time":0.3637316518},
{"learn":[0.06360449158],"iteration":891,"passed_time":2.976784208,"remaining_time":0.3604178189},
{"learn":[0.06355843662],"iteration":892,"passed_time":2.98001853,"remaining_time":0.3570682897},
{"learn":[0.06347751972],"iteration":893,"passed_time":2.983743085,"remaining_time":0.3537771443},
{"learn":[0.06340445086],"iteration":894,"passed_time":2.986983404,"remaining_time":0.3504282206},
{"learn":[0.06334797167],"iteration":895,"passed_time":2.990256166,"remaining_time":0.347083305},
{"learn":[0.06329309571],"iteration":896,"passed_time":2.993346111,"remaining_time":0.3437175579},
{"learn":[0.06326153199],"iteration":897,"passed_time":2.996517734,"remaining_time":0.3403617025},
{"learn":[0.063226737],"iteration":898,"passed_time":2.999586586,"remaining_time":0.336994711},
{"learn":[0.06316902594],"iteration":899,"passed_time":3.002985315,"remaining_time":0.333665035},
{"learn":[0.06314360789],"iteration":900,"passed_time":3.006333811,"remaining_time":0.3303296863},
{"learn":[0.06309368411],"iteration":901,"passed_time":3.009570877,"remaining_time":0.3269822017},
{"learn":[0.06303180709],"iteration":902,"passed_time":3.013088112,"remaining_time":0.3236650574},
{"learn":[0.06298787542],"iteration":903,"passed_time":3.01629518,"remaining_time":0.3203145324},
{"learn":[0.06291959154],"iteration":904,"passed_time":3.019881857,"remaining_time":0.3170041729},
{"learn":[0.06285271901],"iteration":905,"passed_time":3.023212802,"remaining_time":0.3136666704},
{"learn":[0.06279814021],"iteration":906,"passed_time":3.026568287,"remaining_time":0.3103316987},
{"learn":[0.06269374904],"iteration":907,"passed_time":3.029854285,"remaining_time":0.3069896412},
{"learn":[0.06265008353],"iteration":908,"passed_time":3.032900948,"remaining_time":0.3036237472},
{"learn":[0.06256628692],"iteration":909,"passed_time":3.036085518,"remaining_time":0.3002721941},
{"learn":[0.06250273852],"iteration":910,"passed_time":3.039243724,"remaining_time":0.2969184319},
{"learn":[0.06244599934],"iteration":911,"passed_time":3.042351114,"remaining_time":0.2935601952},
{"learn":[0.06241509172],"iteration":912,"passed_time":3.045771334,"remaining_time":0.2902323177},
{"learn":[0.06238763202],"iteration":913,"passed_time":3.049060721,"remaining_time":0.2868919278},
{"learn":[0.06234678304],"iteration":914,"passed_time":3.052338898,"remaining_time":0.283550608},
{"learn":[0.06230911577],"iteration":915,"passed_time":3.055713903,"remaining_time":0.2802183056},
{"learn":[0.06224423651],"iteration":916,"passed_time":3.059092719,"remaining_time":0.2768862548},
{"learn":[0.0622203795],"iteration":917,"passed_time":3.062297947,"remaining_time":0.2735385966},
{"learn":[0.06219852817],"iteration":918,"passed_time":3.065529152,"remaining_time":0.2701935379},
{"learn":[0.06217861309],"iteration":919,"passed_time":3.069089901,"remaining_time":0.2668773827},
{"learn":[0.06216454282],"iteration":920,"passed_time":3.072081309,"remaining_time":0.2635118603},
{"learn":[0.06210592183],"iteration":921,"passed_time":3.075294904,"remaining_time":0.2601659464},
{"learn":[0.06200704608],"iteration":922,"passed_time":3.078790902,"remaining_time":0.2568438781},
{"learn":[0.06196664895],"iteration":923,"passed_time":3.083094587,"remaining_time":0.2535878665},
{"learn":[0.06194175208],"iteration":924,"passed_time":3.086278194,"remaining_time":0.2502387725},
{"learn":[0.06190883897],"iteration":925,"passed_time":3.089588598,"remaining_time":0.2469001687},
{"learn":[0.06188444338],"iteration":926,"passed_time":3.092705927,"remaining_time":0.2435464214},
{"learn":[0.0618305455],"iteration":927,"passed_time":3.095980977,"remaining_time":0.2402054207},
{"learn":[0.06178387156],"iteration":928,"passed_time":3.099289087,"remaining_time":0.2368670885},
{"learn":[0.06174249641],"iteration":929,"passed_time":3.102367515,"remaining_time":0.2335115334},
{"learn":[0.06169078362],"iteration":930,"passed_time":3.105359682,"remaining_time":0.2301501805},
{"learn":[0.06166666669],"iteration":931,"passed_time":3.108268219,"remaining_time":0.2267835182},
{"learn":[0.06160696239],"iteration":932,"passed_time":3.111660866,"remaining_time":0.2234526024},
{"learn":[0.06156603916],"iteration":933,"passed_time":3.115169743,"remaining_time":0.2201297677},
{"learn":[0.06149373774],"iteration":934,"passed_time":3.118331516,"remaining_time":0.2167824049},
{"learn":[0.06147120543],"iteration":935,"passed_time":3.121580026,"remaining_time":0.2134413693},
{"learn":[0.06141384723],"iteration":936,"passed_time":3.125028245,"remaining_time":0.2101139589},
{"learn":[0.06138690758],"iteration":937,"passed_time":3.128150867,"remaining_time":0.2067647694},
{"learn":[0.06133141872],"iteration":938,"passed_time":3.131416107,"remaining_time":0.2034253275},
{"learn":[0.06130166879],"iteration":939,"passed_time":3.134579768,"remaining_time":0.2000795597},
{"learn":[0.0612496465],"iteration":940,"passed_time":3.137622054,"remaining_time":0.1967265687},
{"learn":[0.06122015646],"iteration":941,"passed_time":3.140761974,"remaining_time":0.1933802489},
{"learn":[0.06116468005],"iteration":942,"passed_time":3.159778721,"remaining_time":0.1909940478},
{"learn":[0.06109869275],"iteration":943,"passed_time":3.16313713,"remaining_time":0.187643728},
{"learn":[0.06101415968],"iteration":944,"passed_time":3.166878796,"remaining_time":0.1843156971},
{"learn":[0.06096276882],"iteration":945,"passed_time":3.170638049,"remaining_time":0.1809877956},
{"learn":[0.0609370053],"iteration":946,"passed_time":3.173715832,"remaining_time":0.1776208438},
{"learn":[0.06088792953],"iteration":947,"passed_time":3.176990602,"remaining_time":0.1742653073},
{"learn":[0.06083840189],"iteration":948,"passed_time":3.190220758,"remaining_time":0.1714449512},
{"learn":[0.06077411689],"iteration":949,"passed_time":3.193545493,"remaining_time":0.1680813417},
{"learn":[0.06070377167],"iteration":950,"passed_time":3.196835017,"remaining_time":0.1647159998},
{"learn":[0.06064507526],"iteration":951,"passed_time":3.2001519,"remaining_time":0.1613521966},
{"learn":[0.0606118081],"iteration":952,"passed_time":3.203524884,"remaining_time":0.1579912587},
{"learn":[0.06057817071],"iteration":953,"passed_time":3.221573951,"remaining_time":0.1553379473},
{"learn":[0.0605155075],"iteration":954,"passed_time":3.225103001,"remaining_time":0.1519682042},
{"learn":[0.06045861357],"iteration":955,"passed_time":3.228318774,"remaining_time":0.1485837092},
{"learn":[0.0604002154],"iteration":956,"passed_time":3.236992412,"remaining_time":0.1454448001},
{"learn":[0.06033785555],"iteration":957,"passed_time":3.240365886,"remaining_time":0.1420619699},
{"learn":[0.06027052495],"iteration":958,"passed_time":3.244006046,"remaining_time":0.1386905609},
{"learn":[0.06022254487],"iteration":959,"passed_time":3.247046517,"remaining_time":0.1352936049},
{"learn":[0.06018784277],"iteration":960,"passed_time":3.250236445,"remaining_time":0.1319034561},
{"learn":[0.06013694087],"iteration":961,"passed_time":3.253192331,"remaining_time":0.1285044788},
{"learn":[0.06005832561],"iteration":962,"passed_time":3.256409083,"remaining_time":0.1251164445},
{"learn":[0.06003764422],"iteration":963,"passed_time":3.268271458,"remaining_time":0.1220516312},
{"learn":[0.06001345923],"iteration":964,"passed_time":3.271431091,"remaining_time":0.1186529411},
{"learn":[0.05995884325],"iteration":965,"passed_time":3.275137707,"remaining_time":0.115273998},
{"learn":[0.05992851131],"iteration":966,"passed_time":3.279063571,"remaining_time":0.1119018592},
{"learn":[0.05984770473],"iteration":967,"passed_time":3.282779364,"remaining_time":0.1085216319},
{"learn":[0.05978972133],"iteration":968,"passed_time":3.286371362,"remaining_time":0.1051367515},
{"learn":[0.05974208175],"iteration":969,"passed_time":3.289421048,"remaining_time":0.1017346716},
{"learn":[0.05969464635],"iteration":970,"passed_time":3.292536036,"remaining_time":0.09833526782},
{"learn":[0.05961783865],"iteration":971,"passed_time":3.295496206,"remaining_time":0.09493198948},
{"learn":[0.05956338981],"iteration":972,"passed_time":3.298412058,"remaining_time":0.09152839216},
{"learn":[0.05952120994],"iteration":973,"passed_time":3.301345118,"remaining_time":0.08812625572},
{"learn":[0.059427664],"iteration":974,"passed_time":3.304482087,"remaining_time":0.08473030992},
{"learn":[0.05939764783],"iteration":975,"passed_time":3.307933207,"remaining_time":0.08134261984},
{"learn":[0.05932369374],"iteration":976,"passed_time":3.311169183,"remaining_time":0.07794973513},
{"learn":[0.05924876785],"iteration":977,"passed_time":3.314493649,"remaining_time":0.07455916185},
{"learn":[0.05922439093],"iteration":978,"passed_time":3.317987799,"remaining_time":0.0711723634},
{"learn":[0.05919418899],"iteration":979,"passed_time":3.321119281,"remaining_time":0.0677779445},
{"learn":[0.05913766647],"iteration":980,"passed_time":3.324315295,"remaining_time":0.06438531152},
{"learn":[0.05909153726],"iteration":981,"passed_time":3.327286485,"remaining_time":0.06098895797},
{"learn":[0.05903238385],"iteration":982,"passed_time":3.33027115,"remaining_time":0.0575937025},
{"learn":[0.05900017013],"iteration":983,"passed_time":3.344688264,"remaining_time":0.05438517503},
{"learn":[0.0589652575],"iteration":984,"passed_time":3.347936909,"remaining_time":0.0509838108},
{"learn":[0.05893071627],"iteration":985,"passed_time":3.350824538,"remaining_time":0.04757763036},
{"learn":[0.05890331854],"iteration":986,"passed_time":3.353700313,"remaining_time":0.04417234455},
{"learn":[0.05882211582],"iteration":987,"passed_time":3.356611409,"remaining_time":0.04076855962},
{"learn":[0.05879479237],"iteration":988,"passed_time":3.359416574,"remaining_time":0.03736459284},
{"learn":[0.05875364017],"iteration":989,"passed_time":3.362436967,"remaining_time":0.03396400976},
{"learn":[0.05872604425],"iteration":990,"passed_time":3.36525029,"remaining_time":0.03056231343},
{"learn":[0.05865948749],"iteration":991,"passed_time":3.368315001,"remaining_time":0.02716383066},
{"learn":[0.05860899421],"iteration":992,"passed_time":3.371360255,"remaining_time":0.02376588297},
{"learn":[0.05857287445],"iteration":993,"passed_time":3.374595127,"remaining_time":0.0203697895},
{"learn":[0.05851877845],"iteration":994,"passed_time":3.378217772,"remaining_time":0.0169759687},
{"learn":[0.05848418158],"iteration":995,"passed_time":3.381422718,"remaining_time":0.01358001092},
{"learn":[0.05842906433],"iteration":996,"passed_time":3.384644574,"remaining_time":0.01018448718},
{"learn":[0.05841769917],"iteration":997,"passed_time":3.387654484,"remaining_time":0.006788886742},
{"learn":[0.05838152377],"iteration":998,"passed_time":3.390676216,"remaining_time":0.003394070286},
{"learn":[0.05836348559],"iteration":999,"passed_time":3.393871455,"remaining_time":0}
]}